Workbook

Sheet Léeme
A1: Base de caja y clientes · Pastas Don Aldo
A2: Datos 100% ficticios (generate_pyme.py, semilla fija). Enero a mayo: Excel compartido limpiado con limpiar_excel.py. Junio en adelante: formulario.
A4: Hojas
A5: Cierres: un cierre por local y día, con el arqueo en fórmulas (efectivo esperado, diferencia y si cuadra).
A6: Resumen mensual: venta, efectivo, tickets, costo de plataformas y caja por mes y local, con SUMIFS y COUNTIFS sobre Cierres.
A7: Fiado: lo comprado a cuenta menos lo cobrado, por restaurante; la columna Control compara la fórmula con el motor del tablero.
A8: Pedidos, Cobros y Problemas del Excel: los datos y el registro de cada arreglo de la limpieza.
A10: Supuestos (azul = valor cargado)
A11: Corte de los datos | B11: 45939
A12: Tolerancia para que la caja cuadre ($) | B12: 500
A13: Comisión débito | B13: 0.015
A14: Comisión crédito | B14: 0.035
A15: Comisión billetera virtual | B15: 0.008
A17: Colores: azul = valor cargado · verde = fórmula que lee otra hoja · negro = fórmula de la misma hoja.

Sheet Resumen mensual
A1: Mes | B1: Local | C1: Venta | D1: Efectivo | E1: % efectivo | F1: Tickets | G1: Ticket promedio | H1: Costo plataformas | I1: Cierres con arqueo | J1: Cierres que cuadran | K1: % que cuadra | L1: Faltó en la caja
A2: 2025-01 | B2: Centro | C2: =SUMIFS(Cierres!$J$2:$J$478,Cierres!$A$2:$A$478,">="&DATE(2025,1,1),Cierres!$A$2:$A$478,"<="&EOMONTH(DATE(2025,1,1),0),Cierres!$B$2:$B$478,$B2) -> 11314270 | D2: =SUMIFS(Cierres!$E$2:$E$478,Cierres!$A$2:$A$478,">="&DATE(2025,1,1),Cierres!$A$2:$A$478,"<="&EOMONTH(DATE(2025,1,1),0),Cierres!$B$2:$B$478,$B2) -> 8964820 | E2: =IF(C2=0,"",D2/C2) -> 0.7923463 | F2: =SUMIFS(Cierres!$K$2:$K$478,Cierres!$A$2:$A$478,">="&DATE(2025,1,1),Cierres!$A$2:$A$478,"<="&EOMONTH(DATE(2025,1,1),0),Cierres!$B$2:$B$478,$B2) -> 0 | G2: =IF(F2=0,"",SUMIFS(Cierres!$J$2:$J$478,Cierres!$A$2:$A$478,">="&DATE(2025,1,1),Cierres!$A$2:$A$478,"<="&EOMONTH(DATE(2025,1,1),0),Cierres!$B$2:$B$478,$B2,Cierres!$K$2:$K$478,">0")/F2) | H2: =ROUND(SUMIFS(Cierres!$F$2:$F$478,Cierres!$A$2:$A$478,">="&DATE(2025,1,1),Cierres!$A$2:$A$478,"<="&EOMONTH(DATE(2025,1,1),0),Cierres!$B$2:$B$478,$B2)*Léeme!$B$13+SUMIFS(Cierres!$G$2:$G$478,Cierres!$A$2:$A$478,">="&DATE(2025,1,1),Cierres!$A$2:$A$478,"<="&EOMONTH(DATE(2025,1,1),0),Cierres!$B$2:$B$478,$B2)*Léeme!$B$14+SUMIFS(Cierres!$H$2:$H$478,Cierres!$A$2:$A$478,">="&DATE(2025,1,1),Cierres!$A$2:$A$478,"<="&EOMONTH(DATE(2025,1,1),0),Cierres!$B$2:$B$478,$B2)*Léeme!$B$15,0) -> 33430 | I2: =COUNTIFS(Cierres!$A$2:$A$478,">="&DATE(2025,1,1),Cierres!$A$2:$A$478,"<="&EOMONTH(DATE(2025,1,1),0),Cierres!$B$2:$B$478,$B2,Cierres!$Q$2:$Q$478,"<>") -> 0 | J2: =COUNTIFS(Cierres!$A$2:$A$478,">="&DATE(2025,1,1),Cierres!$A$2:$A$478,"<="&EOMONTH(DATE(2025,1,1),0),Cierres!$B$2:$B$478,$B2,Cierres!$S$2:$S$478,"Cuadra") -> 0 | K2: =IF(I2=0,"",J2/I2) | L2: =-SUMIFS(Cierres!$R$2:$R$478,Cierres!$A$2:$A$478,">="&DATE(2025,1,1),Cierres!$A$2:$A$478,"<="&EOMONTH(DATE(2025,1,1),0),Cierres!$B$2:$B$478,$B2,Cierres!$R$2:$R$478,"<"&-Léeme!$B$12) -> 0
A3: 2025-01 | B3: Jardín | C3: =SUMIFS(Cierres!$J$2:$J$478,Cierres!$A$2:$A$478,">="&DATE(2025,1,1),Cierres!$A$2:$A$478,"<="&EOMONTH(DATE(2025,1,1),0),Cierres!$B$2:$B$478,$B3) -> 8599530 | D3: =SUMIFS(Cierres!$E$2:$E$478,Cierres!$A$2:$A$478,">="&DATE(2025,1,1),Cierres!$A$2:$A$478,"<="&EOMONTH(DATE(2025,1,1),0),Cierres!$B$2:$B$478,$B3) -> 6836090 | E3: =IF(C3=0,"",D3/C3) -> 0.79493763 | F3: =SUMIFS(Cierres!$K$2:$K$478,Cierres!$A$2:$A$478,">="&DATE(2025,1,1),Cierres!$A$2:$A$478,"<="&EOMONTH(DATE(2025,1,1),0),Cierres!$B$2:$B$478,$B3) -> 0 | G3: =IF(F3=0,"",SUMIFS(Cierres!$J$2:$J$478,Cierres!$A$2:$A$478,">="&DATE(2025,1,1),Cierres!$A$2:$A$478,"<="&EOMONTH(DATE(2025,1,1),0),Cierres!$B$2:$B$478,$B3,Cierres!$K$2:$K$478,">0")/F3) | H3: =ROUND(SUMIFS(Cierres!$F$2:$F$478,Cierres!$A$2:$A$478,">="&DATE(2025,1,1),Cierres!$A$2:$A$478,"<="&EOMONTH(DATE(2025,1,1),0),Cierres!$B$2:$B$478,$B3)*Léeme!$B$13+SUMIFS(Cierres!$G$2:$G$478,Cierres!$A$2:$A$478,">="&DATE(2025,1,1),Cierres!$A$2:$A$478,"<="&EOMONTH(DATE(2025,1,1),0),Cierres!$B$2:$B$478,$B3)*Léeme!$B$14+SUMIFS(Cierres!$H$2:$H$478,Cierres!$A$2:$A$478,">="&DATE(2025,1,1),Cierres!$A$2:$A$478,"<="&EOMONTH(DATE(2025,1,1),0),Cierres!$B$2:$B$478,$B3)*Léeme!$B$15,0) -> 25183 | I3: =COUNTIFS(Cierres!$A$2:$A$478,">="&DATE(2025,1,1),Cierres!$A$2:$A$478,"<="&EOMONTH(DATE(2025,1,1),0),Cierres!$B$2:$B$478,$B3,Cierres!$Q$2:$Q$478,"<>") -> 0 | J3: =COUNTIFS(Cierres!$A$2:$A$478,">="&DATE(2025,1,1),Cierres!$A$2:$A$478,"<="&EOMONTH(DATE(2025,1,1),0),Cierres!$B$2:$B$478,$B3,Cierres!$S$2:$S$478,"Cuadra") -> 0 | K3: =IF(I3=0,"",J3/I3) | L3: =-SUMIFS(Cierres!$R$2:$R$478,Cierres!$A$2:$A$478,">="&DATE(2025,1,1),Cierres!$A$2:$A$478,"<="&EOMONTH(DATE(2025,1,1),0),Cierres!$B$2:$B$478,$B3,Cierres!$R$2:$R$478,"<"&-Léeme!$B$12) -> 0
A4: 2025-02 | B4: Centro | C4: =SUMIFS(Cierres!$J$2:$J$478,Cierres!$A$2:$A$478,">="&DATE(2025,2,1),Cierres!$A$2:$A$478,"<="&EOMONTH(DATE(2025,2,1),0),Cierres!$B$2:$B$478,$B4) -> 11221780 | D4: =SUMIFS(Cierres!$E$2:$E$478,Cierres!$A$2:$A$478,">="&DATE(2025,2,1),Cierres!$A$2:$A$478,"<="&EOMONTH(DATE(2025,2,1),0),Cierres!$B$2:$B$478,$B4) -> 8696910 | E4: =IF(C4=0,"",D4/C4) -> 0.77500272 | F4: =SUMIFS(Cierres!$K$2:$K$478,Cierres!$A$2:$A$478,">="&DATE(2025,2,1),Cierres!$A$2:$A$478,"<="&EOMONTH(DATE(2025,2,1),0),Cierres!$B$2:$B$478,$B4) -> 0 | G4: =IF(F4=0,"",SUMIFS(Cierres!$J$2:$J$478,Cierres!$A$2:$A$478,">="&DATE(2025,2,1),Cierres!$A$2:$A$478,"<="&EOMONTH(DATE(2025,2,1),0),Cierres!$B$2:$B$478,$B4,Cierres!$K$2:$K$478,">0")/F4) | H4: =ROUND(SUMIFS(Cierres!$F$2:$F$478,Cierres!$A$2:$A$478,">="&DATE(2025,2,1),Cierres!$A$2:$A$478,"<="&EOMONTH(DATE(2025,2,1),0),Cierres!$B$2:$B$478,$B4)*Léeme!$B$13+SUMIFS(Cierres!$G$2:$G$478,Cierres!$A$2:$A$478,">="&DATE(2025,2,1),Cierres!$A$2:$A$478,"<="&EOMONTH(DATE(2025,2,1),0),Cierres!$B$2:$B$478,$B4)*Léeme!$B$14+SUMIFS(Cierres!$H$2:$H$478,Cierres!$A$2:$A$478,">="&DATE(2025,2,1),Cierres!$A$2:$A$478,"<="&EOMONTH(DATE(2025,2,1),0),Cierres!$B$2:$B$478,$B4)*Léeme!$B$15,0) -> 35168 | I4: =COUNTIFS(Cierres!$A$2:$A$478,">="&DATE(2025,2,1),Cierres!$A$2:$A$478,"<="&EOMONTH(DATE(2025,2,1),0),Cierres!$B$2:$B$478,$B4,Cierres!$Q$2:$Q$478,"<>") -> 0 | J4: =COUNTIFS(Cierres!$A$2:$A$478,">="&DATE(2025,2,1),Cierres!$A$2:$A$478,"<="&EOMONTH(DATE(2025,2,1),0),Cierres!$B$2:$B$478,$B4,Cierres!$S$2:$S$478,"Cuadra") -> 0 | K4: =IF(I4=0,"",J4/I4) | L4: =-SUMIFS(Cierres!$R$2:$R$478,Cierres!$A$2:$A$478,">="&DATE(2025,2,1),Cierres!$A$2:$A$478,"<="&EOMONTH(DATE(2025,2,1),0),Cierres!$B$2:$B$478,$B4,Cierres!$R$2:$R$478,"<"&-Léeme!$B$12) -> 0
A5: 2025-02 | B5: Jardín | C5: =SUMIFS(Cierres!$J$2:$J$478,Cierres!$A$2:$A$478,">="&DATE(2025,2,1),Cierres!$A$2:$A$478,"<="&EOMONTH(DATE(2025,2,1),0),Cierres!$B$2:$B$478,$B5) -> 8567530 | D5: =SUMIFS(Cierres!$E$2:$E$478,Cierres!$A$2:$A$478,">="&DATE(2025,2,1),Cierres!$A$2:$A$478,"<="&EOMONTH(DATE(2025,2,1),0),Cierres!$B$2:$B$478,$B5) -> 6665180 | E5: =IF(C5=0,"",D5/C5) -> 0.77795817 | F5: =SUMIFS(Cierres!$K$2:$K$478,Cierres!$A$2:$A$478,">="&DATE(2025,2,1),Cierres!$A$2:$A$478,"<="&EOMONTH(DATE(2025,2,1),0),Cierres!$B$2:$B$478,$B5) -> 0 | G5: =IF(F5=0,"",SUMIFS(Cierres!$J$2:$J$478,Cierres!$A$2:$A$478,">="&DATE(2025,2,1),Cierres!$A$2:$A$478,"<="&EOMONTH(DATE(2025,2,1),0),Cierres!$B$2:$B$478,$B5,Cierres!$K$2:$K$478,">0")/F5) | H5: =ROUND(SUMIFS(Cierres!$F$2:$F$478,Cierres!$A$2:$A$478,">="&DATE(2025,2,1),Cierres!$A$2:$A$478,"<="&EOMONTH(DATE(2025,2,1),0),Cierres!$B$2:$B$478,$B5)*Léeme!$B$13+SUMIFS(Cierres!$G$2:$G$478,Cierres!$A$2:$A$478,">="&DATE(2025,2,1),Cierres!$A$2:$A$478,"<="&EOMONTH(DATE(2025,2,1),0),Cierres!$B$2:$B$478,$B5)*Léeme!$B$14+SUMIFS(Cierres!$H$2:$H$478,Cierres!$A$2:$A$478,">="&DATE(2025,2,1),Cierres!$A$2:$A$478,"<="&EOMONTH(DATE(2025,2,1),0),Cierres!$B$2:$B$478,$B5)*Léeme!$B$15,0) -> 26805 | I5: =COUNTIFS(Cierres!$A$2:$A$478,">="&DATE(2025,2,1),Cierres!$A$2:$A$478,"<="&EOMONTH(DATE(2025,2,1),0),Cierres!$B$2:$B$478,$B5,Cierres!$Q$2:$Q$478,"<>") -> 0 | J5: =COUNTIFS(Cierres!$A$2:$A$478,">="&DATE(2025,2,1),Cierres!$A$2:$A$478,"<="&EOMONTH(DATE(2025,2,1),0),Cierres!$B$2:$B$478,$B5,Cierres!$S$2:$S$478,"Cuadra") -> 0 | K5: =IF(I5=0,"",J5/I5) | L5: =-SUMIFS(Cierres!$R$2:$R$478,Cierres!$A$2:$A$478,">="&DATE(2025,2,1),Cierres!$A$2:$A$478,"<="&EOMONTH(DATE(2025,2,1),0),Cierres!$B$2:$B$478,$B5,Cierres!$R$2:$R$478,"<"&-Léeme!$B$12) -> 0
A6: 2025-03 | B6: Centro | C6: =SUMIFS(Cierres!$J$2:$J$478,Cierres!$A$2:$A$478,">="&DATE(2025,3,1),Cierres!$A$2:$A$478,"<="&EOMONTH(DATE(2025,3,1),0),Cierres!$B$2:$B$478,$B6) -> 14655980 | D6: =SUMIFS(Cierres!$E$2:$E$478,Cierres!$A$2:$A$478,">="&DATE(2025,3,1),Cierres!$A$2:$A$478,"<="&EOMONTH(DATE(2025,3,1),0),Cierres!$B$2:$B$478,$B6) -> 11256980 | E6: =IF(C6=0,"",D6/C6) -> 0.76808102 | F6: =SUMIFS(Cierres!$K$2:$K$478,Cierres!$A$2:$A$478,">="&DATE(2025,3,1),Cierres!$A$2:$A$478,"<="&EOMONTH(DATE(2025,3,1),0),Cierres!$B$2:$B$478,$B6) -> 0 | G6: =IF(F6=0,"",SUMIFS(Cierres!$J$2:$J$478,Cierres!$A$2:$A$478,">="&DATE(2025,3,1),Cierres!$A$2:$A$478,"<="&EOMONTH(DATE(2025,3,1),0),Cierres!$B$2:$B$478,$B6,Cierres!$K$2:$K$478,">0")/F6) | H6: =ROUND(SUMIFS(Cierres!$F$2:$F$478,Cierres!$A$2:$A$478,">="&DATE(2025,3,1),Cierres!$A$2:$A$478,"<="&EOMONTH(DATE(2025,3,1),0),Cierres!$B$2:$B$478,$B6)*Léeme!$B$13+SUMIFS(Cierres!$G$2:$G$478,Cierres!$A$2:$A$478,">="&DATE(2025,3,1),Cierres!$A$2:$A$478,"<="&EOMONTH(DATE(2025,3,1),0),Cierres!$B$2:$B$478,$B6)*Léeme!$B$14+SUMIFS(Cierres!$H$2:$H$478,Cierres!$A$2:$A$478,">="&DATE(2025,3,1),Cierres!$A$2:$A$478,"<="&EOMONTH(DATE(2025,3,1),0),Cierres!$B$2:$B$478,$B6)*Léeme!$B$15,0) -> 46400 | I6: =COUNTIFS(Cierres!$A$2:$A$478,">="&DATE(2025,3,1),Cierres!$A$2:$A$478,"<="&EOMONTH(DATE(2025,3,1),0),Cierres!$B$2:$B$478,$B6,Cierres!$Q$2:$Q$478,"<>") -> 0 | J6: =COUNTIFS(Cierres!$A$2:$A$478,">="&DATE(2025,3,1),Cierres!$A$2:$A$478,"<="&EOMONTH(DATE(2025,3,1),0),Cierres!$B$2:$B$478,$B6,Cierres!$S$2:$S$478,"Cuadra") -> 0 | K6: =IF(I6=0,"",J6/I6) | L6: =-SUMIFS(Cierres!$R$2:$R$478,Cierres!$A$2:$A$478,">="&DATE(2025,3,1),Cierres!$A$2:$A$478,"<="&EOMONTH(DATE(2025,3,1),0),Cierres!$B$2:$B$478,$B6,Cierres!$R$2:$R$478,"<"&-Léeme!$B$12) -> 0
A7: 2025-03 | B7: Jardín | C7: =SUMIFS(Cierres!$J$2:$J$478,Cierres!$A$2:$A$478,">="&DATE(2025,3,1),Cierres!$A$2:$A$478,"<="&EOMONTH(DATE(2025,3,1),0),Cierres!$B$2:$B$478,$B7) -> 11237260 | D7: =SUMIFS(Cierres!$E$2:$E$478,Cierres!$A$2:$A$478,">="&DATE(2025,3,1),Cierres!$A$2:$A$478,"<="&EOMONTH(DATE(2025,3,1),0),Cierres!$B$2:$B$478,$B7) -> 8564250 | E7: =IF(C7=0,"",D7/C7) -> 0.76212974 | F7: =SUMIFS(Cierres!$K$2:$K$478,Cierres!$A$2:$A$478,">="&DATE(2025,3,1),Cierres!$A$2:$A$478,"<="&EOMONTH(DATE(2025,3,1),0),Cierres!$B$2:$B$478,$B7) -> 0 | G7: =IF(F7=0,"",SUMIFS(Cierres!$J$2:$J$478,Cierres!$A$2:$A$478,">="&DATE(2025,3,1),Cierres!$A$2:$A$478,"<="&EOMONTH(DATE(2025,3,1),0),Cierres!$B$2:$B$478,$B7,Cierres!$K$2:$K$478,">0")/F7) | H7: =ROUND(SUMIFS(Cierres!$F$2:$F$478,Cierres!$A$2:$A$478,">="&DATE(2025,3,1),Cierres!$A$2:$A$478,"<="&EOMONTH(DATE(2025,3,1),0),Cierres!$B$2:$B$478,$B7)*Léeme!$B$13+SUMIFS(Cierres!$G$2:$G$478,Cierres!$A$2:$A$478,">="&DATE(2025,3,1),Cierres!$A$2:$A$478,"<="&EOMONTH(DATE(2025,3,1),0),Cierres!$B$2:$B$478,$B7)*Léeme!$B$14+SUMIFS(Cierres!$H$2:$H$478,Cierres!$A$2:$A$478,">="&DATE(2025,3,1),Cierres!$A$2:$A$478,"<="&EOMONTH(DATE(2025,3,1),0),Cierres!$B$2:$B$478,$B7)*Léeme!$B$15,0) -> 36528 | I7: =COUNTIFS(Cierres!$A$2:$A$478,">="&DATE(2025,3,1),Cierres!$A$2:$A$478,"<="&EOMONTH(DATE(2025,3,1),0),Cierres!$B$2:$B$478,$B7,Cierres!$Q$2:$Q$478,"<>") -> 0 | J7: =COUNTIFS(Cierres!$A$2:$A$478,">="&DATE(2025,3,1),Cierres!$A$2:$A$478,"<="&EOMONTH(DATE(2025,3,1),0),Cierres!$B$2:$B$478,$B7,Cierres!$S$2:$S$478,"Cuadra") -> 0 | K7: =IF(I7=0,"",J7/I7) | L7: =-SUMIFS(Cierres!$R$2:$R$478,Cierres!$A$2:$A$478,">="&DATE(2025,3,1),Cierres!$A$2:$A$478,"<="&EOMONTH(DATE(2025,3,1),0),Cierres!$B$2:$B$478,$B7,Cierres!$R$2:$R$478,"<"&-Léeme!$B$12) -> 0
A8: 2025-04 | B8: Centro | C8: =SUMIFS(Cierres!$J$2:$J$478,Cierres!$A$2:$A$478,">="&DATE(2025,4,1),Cierres!$A$2:$A$478,"<="&EOMONTH(DATE(2025,4,1),0),Cierres!$B$2:$B$478,$B8) -> 14115060 | D8: =SUMIFS(Cierres!$E$2:$E$478,Cierres!$A$2:$A$478,">="&DATE(2025,4,1),Cierres!$A$2:$A$478,"<="&EOMONTH(DATE(2025,4,1),0),Cierres!$B$2:$B$478,$B8) -> 10579610 | E8: =IF(C8=0,"",D8/C8) -> 0.74952639 | F8: =SUMIFS(Cierres!$K$2:$K$478,Cierres!$A$2:$A$478,">="&DATE(2025,4,1),Cierres!$A$2:$A$478,"<="&EOMONTH(DATE(2025,4,1),0),Cierres!$B$2:$B$478,$B8) -> 0 | G8: =IF(F8=0,"",SUMIFS(Cierres!$J$2:$J$478,Cierres!$A$2:$A$478,">="&DATE(2025,4,1),Cierres!$A$2:$A$478,"<="&EOMONTH(DATE(2025,4,1),0),Cierres!$B$2:$B$478,$B8,Cierres!$K$2:$K$478,">0")/F8) | H8: =ROUND(SUMIFS(Cierres!$F$2:$F$478,Cierres!$A$2:$A$478,">="&DATE(2025,4,1),Cierres!$A$2:$A$478,"<="&EOMONTH(DATE(2025,4,1),0),Cierres!$B$2:$B$478,$B8)*Léeme!$B$13+SUMIFS(Cierres!$G$2:$G$478,Cierres!$A$2:$A$478,">="&DATE(2025,4,1),Cierres!$A$2:$A$478,"<="&EOMONTH(DATE(2025,4,1),0),Cierres!$B$2:$B$478,$B8)*Léeme!$B$14+SUMIFS(Cierres!$H$2:$H$478,Cierres!$A$2:$A$478,">="&DATE(2025,4,1),Cierres!$A$2:$A$478,"<="&EOMONTH(DATE(2025,4,1),0),Cierres!$B$2:$B$478,$B8)*Léeme!$B$15,0) -> 54450 | I8: =COUNTIFS(Cierres!$A$2:$A$478,">="&DATE(2025,4,1),Cierres!$A$2:$A$478,"<="&EOMONTH(DATE(2025,4,1),0),Cierres!$B$2:$B$478,$B8,Cierres!$Q$2:$Q$478,"<>") -> 0 | J8: =COUNTIFS(Cierres!$A$2:$A$478,">="&DATE(2025,4,1),Cierres!$A$2:$A$478,"<="&EOMONTH(DATE(2025,4,1),0),Cierres!$B$2:$B$478,$B8,Cierres!$S$2:$S$478,"Cuadra") -> 0 | K8: =IF(I8=0,"",J8/I8) | L8: =-SUMIFS(Cierres!$R$2:$R$478,Cierres!$A$2:$A$478,">="&DATE(2025,4,1),Cierres!$A$2:$A$478,"<="&EOMONTH(DATE(2025,4,1),0),Cierres!$B$2:$B$478,$B8,Cierres!$R$2:$R$478,"<"&-Léeme!$B$12) -> 0
A9: 2025-04 | B9: Jardín | C9: =SUMIFS(Cierres!$J$2:$J$478,Cierres!$A$2:$A$478,">="&DATE(2025,4,1),Cierres!$A$2:$A$478,"<="&EOMONTH(DATE(2025,4,1),0),Cierres!$B$2:$B$478,$B9) -> 10695830 | D9: =SUMIFS(Cierres!$E$2:$E$478,Cierres!$A$2:$A$478,">="&DATE(2025,4,1),Cierres!$A$2:$A$478,"<="&EOMONTH(DATE(2025,4,1),0),Cierres!$B$2:$B$478,$B9) -> 8001710 | E9: =IF(C9=0,"",D9/C9) -> 0.74811492 | F9: =SUMIFS(Cierres!$K$2:$K$478,Cierres!$A$2:$A$478,">="&DATE(2025,4,1),Cierres!$A$2:$A$478,"<="&EOMONTH(DATE(2025,4,1),0),Cierres!$B$2:$B$478,$B9) -> 0 | G9: =IF(F9=0,"",SUMIFS(Cierres!$J$2:$J$478,Cierres!$A$2:$A$478,">="&DATE(2025,4,1),Cierres!$A$2:$A$478,"<="&EOMONTH(DATE(2025,4,1),0),Cierres!$B$2:$B$478,$B9,Cierres!$K$2:$K$478,">0")/F9) | H9: =ROUND(SUMIFS(Cierres!$F$2:$F$478,Cierres!$A$2:$A$478,">="&DATE(2025,4,1),Cierres!$A$2:$A$478,"<="&EOMONTH(DATE(2025,4,1),0),Cierres!$B$2:$B$478,$B9)*Léeme!$B$13+SUMIFS(Cierres!$G$2:$G$478,Cierres!$A$2:$A$478,">="&DATE(2025,4,1),Cierres!$A$2:$A$478,"<="&EOMONTH(DATE(2025,4,1),0),Cierres!$B$2:$B$478,$B9)*Léeme!$B$14+SUMIFS(Cierres!$H$2:$H$478,Cierres!$A$2:$A$478,">="&DATE(2025,4,1),Cierres!$A$2:$A$478,"<="&EOMONTH(DATE(2025,4,1),0),Cierres!$B$2:$B$478,$B9)*Léeme!$B$15,0) -> 41407 | I9: =COUNTIFS(Cierres!$A$2:$A$478,">="&DATE(2025,4,1),Cierres!$A$2:$A$478,"<="&EOMONTH(DATE(2025,4,1),0),Cierres!$B$2:$B$478,$B9,Cierres!$Q$2:$Q$478,"<>") -> 0 | J9: =COUNTIFS(Cierres!$A$2:$A$478,">="&DATE(2025,4,1),Cierres!$A$2:$A$478,"<="&EOMONTH(DATE(2025,4,1),0),Cierres!$B$2:$B$478,$B9,Cierres!$S$2:$S$478,"Cuadra") -> 0 | K9: =IF(I9=0,"",J9/I9) | L9: =-SUMIFS(Cierres!$R$2:$R$478,Cierres!$A$2:$A$478,">="&DATE(2025,4,1),Cierres!$A$2:$A$478,"<="&EOMONTH(DATE(2025,4,1),0),Cierres!$B$2:$B$478,$B9,Cierres!$R$2:$R$478,"<"&-Léeme!$B$12) -> 0
A10: 2025-05 | B10: Centro | C10: =SUMIFS(Cierres!$J$2:$J$478,Cierres!$A$2:$A$478,">="&DATE(2025,5,1),Cierres!$A$2:$A$478,"<="&EOMONTH(DATE(2025,5,1),0),Cierres!$B$2:$B$478,$B10) -> 15047670 | D10: =SUMIFS(Cierres!$E$2:$E$478,Cierres!$A$2:$A$478,">="&DATE(2025,5,1),Cierres!$A$2:$A$478,"<="&EOMONTH(DATE(2025,5,1),0),Cierres!$B$2:$B$478,$B10) -> 10966140 | E10: =IF(C10=0,"",D10/C10) -> 0.72876 | F10: =SUMIFS(Cierres!$K$2:$K$478,Cierres!$A$2:$A$478,">="&DATE(2025,5,1),Cierres!$A$2:$A$478,"<="&EOMONTH(DATE(2025,5,1),0),Cierres!$B$2:$B$478,$B10) -> 0 | G10: =IF(F10=0,"",SUMIFS(Cierres!$J$2:$J$478,Cierres!$A$2:$A$478,">="&DATE(2025,5,1),Cierres!$A$2:$A$478,"<="&EOMONTH(DATE(2025,5,1),0),Cierres!$B$2:$B$478,$B10,Cierres!$K$2:$K$478,">0")/F10) | H10: =ROUND(SUMIFS(Cierres!$F$2:$F$478,Cierres!$A$2:$A$478,">="&DATE(2025,5,1),Cierres!$A$2:$A$478,"<="&EOMONTH(DATE(2025,5,1),0),Cierres!$B$2:$B$478,$B10)*Léeme!$B$13+SUMIFS(Cierres!$G$2:$G$478,Cierres!$A$2:$A$478,">="&DATE(2025,5,1),Cierres!$A$2:$A$478,"<="&EOMONTH(DATE(2025,5,1),0),Cierres!$B$2:$B$478,$B10)*Léeme!$B$14+SUMIFS(Cierres!$H$2:$H$478,Cierres!$A$2:$A$478,">="&DATE(2025,5,1),Cierres!$A$2:$A$478,"<="&EOMONTH(DATE(2025,5,1),0),Cierres!$B$2:$B$478,$B10)*Léeme!$B$15,0) -> 62233 | I10: =COUNTIFS(Cierres!$A$2:$A$478,">="&DATE(2025,5,1),Cierres!$A$2:$A$478,"<="&EOMONTH(DATE(2025,5,1),0),Cierres!$B$2:$B$478,$B10,Cierres!$Q$2:$Q$478,"<>") -> 0 | J10: =COUNTIFS(Cierres!$A$2:$A$478,">="&DATE(2025,5,1),Cierres!$A$2:$A$478,"<="&EOMONTH(DATE(2025,5,1),0),Cierres!$B$2:$B$478,$B10,Cierres!$S$2:$S$478,"Cuadra") -> 0 | K10: =IF(I10=0,"",J10/I10) | L10: =-SUMIFS(Cierres!$R$2:$R$478,Cierres!$A$2:$A$478,">="&DATE(2025,5,1),Cierres!$A$2:$A$478,"<="&EOMONTH(DATE(2025,5,1),0),Cierres!$B$2:$B$478,$B10,Cierres!$R$2:$R$478,"<"&-Léeme!$B$12) -> 0
A11: 2025-05 | B11: Jardín | C11: =SUMIFS(Cierres!$J$2:$J$478,Cierres!$A$2:$A$478,">="&DATE(2025,5,1),Cierres!$A$2:$A$478,"<="&EOMONTH(DATE(2025,5,1),0),Cierres!$B$2:$B$478,$B11) -> 11204450 | D11: =SUMIFS(Cierres!$E$2:$E$478,Cierres!$A$2:$A$478,">="&DATE(2025,5,1),Cierres!$A$2:$A$478,"<="&EOMONTH(DATE(2025,5,1),0),Cierres!$B$2:$B$478,$B11) -> 8106510 | E11: =IF(C11=0,"",D11/C11) -> 0.72350807 | F11: =SUMIFS(Cierres!$K$2:$K$478,Cierres!$A$2:$A$478,">="&DATE(2025,5,1),Cierres!$A$2:$A$478,"<="&EOMONTH(DATE(2025,5,1),0),Cierres!$B$2:$B$478,$B11) -> 0 | G11: =IF(F11=0,"",SUMIFS(Cierres!$J$2:$J$478,Cierres!$A$2:$A$478,">="&DATE(2025,5,1),Cierres!$A$2:$A$478,"<="&EOMONTH(DATE(2025,5,1),0),Cierres!$B$2:$B$478,$B11,Cierres!$K$2:$K$478,">0")/F11) | H11: =ROUND(SUMIFS(Cierres!$F$2:$F$478,Cierres!$A$2:$A$478,">="&DATE(2025,5,1),Cierres!$A$2:$A$478,"<="&EOMONTH(DATE(2025,5,1),0),Cierres!$B$2:$B$478,$B11)*Léeme!$B$13+SUMIFS(Cierres!$G$2:$G$478,Cierres!$A$2:$A$478,">="&DATE(2025,5,1),Cierres!$A$2:$A$478,"<="&EOMONTH(DATE(2025,5,1),0),Cierres!$B$2:$B$478,$B11)*Léeme!$B$14+SUMIFS(Cierres!$H$2:$H$478,Cierres!$A$2:$A$478,">="&DATE(2025,5,1),Cierres!$A$2:$A$478,"<="&EOMONTH(DATE(2025,5,1),0),Cierres!$B$2:$B$478,$B11)*Léeme!$B$15,0) -> 47311 | I11: =COUNTIFS(Cierres!$A$2:$A$478,">="&DATE(2025,5,1),Cierres!$A$2:$A$478,"<="&EOMONTH(DATE(2025,5,1),0),Cierres!$B$2:$B$478,$B11,Cierres!$Q$2:$Q$478,"<>") -> 0 | J11: =COUNTIFS(Cierres!$A$2:$A$478,">="&DATE(2025,5,1),Cierres!$A$2:$A$478,"<="&EOMONTH(DATE(2025,5,1),0),Cierres!$B$2:$B$478,$B11,Cierres!$S$2:$S$478,"Cuadra") -> 0 | K11: =IF(I11=0,"",J11/I11) | L11: =-SUMIFS(Cierres!$R$2:$R$478,Cierres!$A$2:$A$478,">="&DATE(2025,5,1),Cierres!$A$2:$A$478,"<="&EOMONTH(DATE(2025,5,1),0),Cierres!$B$2:$B$478,$B11,Cierres!$R$2:$R$478,"<"&-Léeme!$B$12) -> 0
A12: 2025-06 | B12: Centro | C12: =SUMIFS(Cierres!$J$2:$J$478,Cierres!$A$2:$A$478,">="&DATE(2025,6,1),Cierres!$A$2:$A$478,"<="&EOMONTH(DATE(2025,6,1),0),Cierres!$B$2:$B$478,$B12) -> 17099330 | D12: =SUMIFS(Cierres!$E$2:$E$478,Cierres!$A$2:$A$478,">="&DATE(2025,6,1),Cierres!$A$2:$A$478,"<="&EOMONTH(DATE(2025,6,1),0),Cierres!$B$2:$B$478,$B12) -> 12287290 | E12: =IF(C12=0,"",D12/C12) -> 0.71858313 | F12: =SUMIFS(Cierres!$K$2:$K$478,Cierres!$A$2:$A$478,">="&DATE(2025,6,1),Cierres!$A$2:$A$478,"<="&EOMONTH(DATE(2025,6,1),0),Cierres!$B$2:$B$478,$B12) -> 1710 | G12: =IF(F12=0,"",SUMIFS(Cierres!$J$2:$J$478,Cierres!$A$2:$A$478,">="&DATE(2025,6,1),Cierres!$A$2:$A$478,"<="&EOMONTH(DATE(2025,6,1),0),Cierres!$B$2:$B$478,$B12,Cierres!$K$2:$K$478,">0")/F12) -> 9999.6082 | H12: =ROUND(SUMIFS(Cierres!$F$2:$F$478,Cierres!$A$2:$A$478,">="&DATE(2025,6,1),Cierres!$A$2:$A$478,"<="&EOMONTH(DATE(2025,6,1),0),Cierres!$B$2:$B$478,$B12)*Léeme!$B$13+SUMIFS(Cierres!$G$2:$G$478,Cierres!$A$2:$A$478,">="&DATE(2025,6,1),Cierres!$A$2:$A$478,"<="&EOMONTH(DATE(2025,6,1),0),Cierres!$B$2:$B$478,$B12)*Léeme!$B$14+SUMIFS(Cierres!$H$2:$H$478,Cierres!$A$2:$A$478,">="&DATE(2025,6,1),Cierres!$A$2:$A$478,"<="&EOMONTH(DATE(2025,6,1),0),Cierres!$B$2:$B$478,$B12)*Léeme!$B$15,0) -> 72454 | I12: =COUNTIFS(Cierres!$A$2:$A$478,">="&DATE(2025,6,1),Cierres!$A$2:$A$478,"<="&EOMONTH(DATE(2025,6,1),0),Cierres!$B$2:$B$478,$B12,Cierres!$Q$2:$Q$478,"<>") -> 25 | J12: =COUNTIFS(Cierres!$A$2:$A$478,">="&DATE(2025,6,1),Cierres!$A$2:$A$478,"<="&EOMONTH(DATE(2025,6,1),0),Cierres!$B$2:$B$478,$B12,Cierres!$S$2:$S$478,"Cuadra") -> 16 | K12: =IF(I12=0,"",J12/I12) -> 0.64 | L12: =-SUMIFS(Cierres!$R$2:$R$478,Cierres!$A$2:$A$478,">="&DATE(2025,6,1),Cierres!$A$2:$A$478,"<="&EOMONTH(DATE(2025,6,1),0),Cierres!$B$2:$B$478,$B12,Cierres!$R$2:$R$478,"<"&-Léeme!$B$12) -> 41850
A13: 2025-06 | B13: Jardín | C13: =SUMIFS(Cierres!$J$2:$J$478,Cierres!$A$2:$A$478,">="&DATE(2025,6,1),Cierres!$A$2:$A$478,"<="&EOMONTH(DATE(2025,6,1),0),Cierres!$B$2:$B$478,$B13) -> 13025470 | D13: =SUMIFS(Cierres!$E$2:$E$478,Cierres!$A$2:$A$478,">="&DATE(2025,6,1),Cierres!$A$2:$A$478,"<="&EOMONTH(DATE(2025,6,1),0),Cierres!$B$2:$B$478,$B13) -> 9371110 | E13: =IF(C13=0,"",D13/C13) -> 0.71944506 | F13: =SUMIFS(Cierres!$K$2:$K$478,Cierres!$A$2:$A$478,">="&DATE(2025,6,1),Cierres!$A$2:$A$478,"<="&EOMONTH(DATE(2025,6,1),0),Cierres!$B$2:$B$478,$B13) -> 1303 | G13: =IF(F13=0,"",SUMIFS(Cierres!$J$2:$J$478,Cierres!$A$2:$A$478,">="&DATE(2025,6,1),Cierres!$A$2:$A$478,"<="&EOMONTH(DATE(2025,6,1),0),Cierres!$B$2:$B$478,$B13,Cierres!$K$2:$K$478,">0")/F13) -> 9996.5234 | H13: =ROUND(SUMIFS(Cierres!$F$2:$F$478,Cierres!$A$2:$A$478,">="&DATE(2025,6,1),Cierres!$A$2:$A$478,"<="&EOMONTH(DATE(2025,6,1),0),Cierres!$B$2:$B$478,$B13)*Léeme!$B$13+SUMIFS(Cierres!$G$2:$G$478,Cierres!$A$2:$A$478,">="&DATE(2025,6,1),Cierres!$A$2:$A$478,"<="&EOMONTH(DATE(2025,6,1),0),Cierres!$B$2:$B$478,$B13)*Léeme!$B$14+SUMIFS(Cierres!$H$2:$H$478,Cierres!$A$2:$A$478,">="&DATE(2025,6,1),Cierres!$A$2:$A$478,"<="&EOMONTH(DATE(2025,6,1),0),Cierres!$B$2:$B$478,$B13)*Léeme!$B$15,0) -> 55047 | I13: =COUNTIFS(Cierres!$A$2:$A$478,">="&DATE(2025,6,1),Cierres!$A$2:$A$478,"<="&EOMONTH(DATE(2025,6,1),0),Cierres!$B$2:$B$478,$B13,Cierres!$Q$2:$Q$478,"<>") -> 25 | J13: =COUNTIFS(Cierres!$A$2:$A$478,">="&DATE(2025,6,1),Cierres!$A$2:$A$478,"<="&EOMONTH(DATE(2025,6,1),0),Cierres!$B$2:$B$478,$B13,Cierres!$S$2:$S$478,"Cuadra") -> 20 | K13: =IF(I13=0,"",J13/I13) -> 0.8 | L13: =-SUMIFS(Cierres!$R$2:$R$478,Cierres!$A$2:$A$478,">="&DATE(2025,6,1),Cierres!$A$2:$A$478,"<="&EOMONTH(DATE(2025,6,1),0),Cierres!$B$2:$B$478,$B13,Cierres!$R$2:$R$478,"<"&-Léeme!$B$12) -> 5140
A14: 2025-07 | B14: Centro | C14: =SUMIFS(Cierres!$J$2:$J$478,Cierres!$A$2:$A$478,">="&DATE(2025,7,1),Cierres!$A$2:$A$478,"<="&EOMONTH(DATE(2025,7,1),0),Cierres!$B$2:$B$478,$B14) -> 18266410 | D14: =SUMIFS(Cierres!$E$2:$E$478,Cierres!$A$2:$A$478,">="&DATE(2025,7,1),Cierres!$A$2:$A$478,"<="&EOMONTH(DATE(2025,7,1),0),Cierres!$B$2:$B$478,$B14) -> 12780330 | E14: =IF(C14=0,"",D14/C14) -> 0.69966293 | F14: =SUMIFS(Cierres!$K$2:$K$478,Cierres!$A$2:$A$478,">="&DATE(2025,7,1),Cierres!$A$2:$A$478,"<="&EOMONTH(DATE(2025,7,1),0),Cierres!$B$2:$B$478,$B14) -> 1773 | G14: =IF(F14=0,"",SUMIFS(Cierres!$J$2:$J$478,Cierres!$A$2:$A$478,">="&DATE(2025,7,1),Cierres!$A$2:$A$478,"<="&EOMONTH(DATE(2025,7,1),0),Cierres!$B$2:$B$478,$B14,Cierres!$K$2:$K$478,">0")/F14) -> 10302.544 | H14: =ROUND(SUMIFS(Cierres!$F$2:$F$478,Cierres!$A$2:$A$478,">="&DATE(2025,7,1),Cierres!$A$2:$A$478,"<="&EOMONTH(DATE(2025,7,1),0),Cierres!$B$2:$B$478,$B14)*Léeme!$B$13+SUMIFS(Cierres!$G$2:$G$478,Cierres!$A$2:$A$478,">="&DATE(2025,7,1),Cierres!$A$2:$A$478,"<="&EOMONTH(DATE(2025,7,1),0),Cierres!$B$2:$B$478,$B14)*Léeme!$B$14+SUMIFS(Cierres!$H$2:$H$478,Cierres!$A$2:$A$478,">="&DATE(2025,7,1),Cierres!$A$2:$A$478,"<="&EOMONTH(DATE(2025,7,1),0),Cierres!$B$2:$B$478,$B14)*Léeme!$B$15,0) -> 82006 | I14: =COUNTIFS(Cierres!$A$2:$A$478,">="&DATE(2025,7,1),Cierres!$A$2:$A$478,"<="&EOMONTH(DATE(2025,7,1),0),Cierres!$B$2:$B$478,$B14,Cierres!$Q$2:$Q$478,"<>") -> 27 | J14: =COUNTIFS(Cierres!$A$2:$A$478,">="&DATE(2025,7,1),Cierres!$A$2:$A$478,"<="&EOMONTH(DATE(2025,7,1),0),Cierres!$B$2:$B$478,$B14,Cierres!$S$2:$S$478,"Cuadra") -> 15 | K14: =IF(I14=0,"",J14/I14) -> 0.55555556 | L14: =-SUMIFS(Cierres!$R$2:$R$478,Cierres!$A$2:$A$478,">="&DATE(2025,7,1),Cierres!$A$2:$A$478,"<="&EOMONTH(DATE(2025,7,1),0),Cierres!$B$2:$B$478,$B14,Cierres!$R$2:$R$478,"<"&-Léeme!$B$12) -> 25990
A15: 2025-07 | B15: Jardín | C15: =SUMIFS(Cierres!$J$2:$J$478,Cierres!$A$2:$A$478,">="&DATE(2025,7,1),Cierres!$A$2:$A$478,"<="&EOMONTH(DATE(2025,7,1),0),Cierres!$B$2:$B$478,$B15) -> 14306490 | D15: =SUMIFS(Cierres!$E$2:$E$478,Cierres!$A$2:$A$478,">="&DATE(2025,7,1),Cierres!$A$2:$A$478,"<="&EOMONTH(DATE(2025,7,1),0),Cierres!$B$2:$B$478,$B15) -> 9962280 | E15: =IF(C15=0,"",D15/C15) -> 0.6963469 | F15: =SUMIFS(Cierres!$K$2:$K$478,Cierres!$A$2:$A$478,">="&DATE(2025,7,1),Cierres!$A$2:$A$478,"<="&EOMONTH(DATE(2025,7,1),0),Cierres!$B$2:$B$478,$B15) -> 1403 | G15: =IF(F15=0,"",SUMIFS(Cierres!$J$2:$J$478,Cierres!$A$2:$A$478,">="&DATE(2025,7,1),Cierres!$A$2:$A$478,"<="&EOMONTH(DATE(2025,7,1),0),Cierres!$B$2:$B$478,$B15,Cierres!$K$2:$K$478,">0")/F15) -> 10197.071 | H15: =ROUND(SUMIFS(Cierres!$F$2:$F$478,Cierres!$A$2:$A$478,">="&DATE(2025,7,1),Cierres!$A$2:$A$478,"<="&EOMONTH(DATE(2025,7,1),0),Cierres!$B$2:$B$478,$B15)*Léeme!$B$13+SUMIFS(Cierres!$G$2:$G$478,Cierres!$A$2:$A$478,">="&DATE(2025,7,1),Cierres!$A$2:$A$478,"<="&EOMONTH(DATE(2025,7,1),0),Cierres!$B$2:$B$478,$B15)*Léeme!$B$14+SUMIFS(Cierres!$H$2:$H$478,Cierres!$A$2:$A$478,">="&DATE(2025,7,1),Cierres!$A$2:$A$478,"<="&EOMONTH(DATE(2025,7,1),0),Cierres!$B$2:$B$478,$B15)*Léeme!$B$15,0) -> 64970 | I15: =COUNTIFS(Cierres!$A$2:$A$478,">="&DATE(2025,7,1),Cierres!$A$2:$A$478,"<="&EOMONTH(DATE(2025,7,1),0),Cierres!$B$2:$B$478,$B15,Cierres!$Q$2:$Q$478,"<>") -> 27 | J15: =COUNTIFS(Cierres!$A$2:$A$478,">="&DATE(2025,7,1),Cierres!$A$2:$A$478,"<="&EOMONTH(DATE(2025,7,1),0),Cierres!$B$2:$B$478,$B15,Cierres!$S$2:$S$478,"Cuadra") -> 22 | K15: =IF(I15=0,"",J15/I15) -> 0.81481481 | L15: =-SUMIFS(Cierres!$R$2:$R$478,Cierres!$A$2:$A$478,">="&DATE(2025,7,1),Cierres!$A$2:$A$478,"<="&EOMONTH(DATE(2025,7,1),0),Cierres!$B$2:$B$478,$B15,Cierres!$R$2:$R$478,"<"&-Léeme!$B$12) -> 3520
A16: 2025-08 | B16: Centro | C16: =SUMIFS(Cierres!$J$2:$J$478,Cierres!$A$2:$A$478,">="&DATE(2025,8,1),Cierres!$A$2:$A$478,"<="&EOMONTH(DATE(2025,8,1),0),Cierres!$B$2:$B$478,$B16) -> 19523500 | D16: =SUMIFS(Cierres!$E$2:$E$478,Cierres!$A$2:$A$478,">="&DATE(2025,8,1),Cierres!$A$2:$A$478,"<="&EOMONTH(DATE(2025,8,1),0),Cierres!$B$2:$B$478,$B16) -> 13473090 | E16: =IF(C16=0,"",D16/C16) -> 0.69009604 | F16: =SUMIFS(Cierres!$K$2:$K$478,Cierres!$A$2:$A$478,">="&DATE(2025,8,1),Cierres!$A$2:$A$478,"<="&EOMONTH(DATE(2025,8,1),0),Cierres!$B$2:$B$478,$B16) -> 1861 | G16: =IF(F16=0,"",SUMIFS(Cierres!$J$2:$J$478,Cierres!$A$2:$A$478,">="&DATE(2025,8,1),Cierres!$A$2:$A$478,"<="&EOMONTH(DATE(2025,8,1),0),Cierres!$B$2:$B$478,$B16,Cierres!$K$2:$K$478,">0")/F16) -> 10490.865 | H16: =ROUND(SUMIFS(Cierres!$F$2:$F$478,Cierres!$A$2:$A$478,">="&DATE(2025,8,1),Cierres!$A$2:$A$478,"<="&EOMONTH(DATE(2025,8,1),0),Cierres!$B$2:$B$478,$B16)*Léeme!$B$13+SUMIFS(Cierres!$G$2:$G$478,Cierres!$A$2:$A$478,">="&DATE(2025,8,1),Cierres!$A$2:$A$478,"<="&EOMONTH(DATE(2025,8,1),0),Cierres!$B$2:$B$478,$B16)*Léeme!$B$14+SUMIFS(Cierres!$H$2:$H$478,Cierres!$A$2:$A$478,">="&DATE(2025,8,1),Cierres!$A$2:$A$478,"<="&EOMONTH(DATE(2025,8,1),0),Cierres!$B$2:$B$478,$B16)*Léeme!$B$15,0) -> 89750 | I16: =COUNTIFS(Cierres!$A$2:$A$478,">="&DATE(2025,8,1),Cierres!$A$2:$A$478,"<="&EOMONTH(DATE(2025,8,1),0),Cierres!$B$2:$B$478,$B16,Cierres!$Q$2:$Q$478,"<>") -> 27 | J16: =COUNTIFS(Cierres!$A$2:$A$478,">="&DATE(2025,8,1),Cierres!$A$2:$A$478,"<="&EOMONTH(DATE(2025,8,1),0),Cierres!$B$2:$B$478,$B16,Cierres!$S$2:$S$478,"Cuadra") -> 17 | K16: =IF(I16=0,"",J16/I16) -> 0.62962963 | L16: =-SUMIFS(Cierres!$R$2:$R$478,Cierres!$A$2:$A$478,">="&DATE(2025,8,1),Cierres!$A$2:$A$478,"<="&EOMONTH(DATE(2025,8,1),0),Cierres!$B$2:$B$478,$B16,Cierres!$R$2:$R$478,"<"&-Léeme!$B$12) -> 67100
A17: 2025-08 | B17: Jardín | C17: =SUMIFS(Cierres!$J$2:$J$478,Cierres!$A$2:$A$478,">="&DATE(2025,8,1),Cierres!$A$2:$A$478,"<="&EOMONTH(DATE(2025,8,1),0),Cierres!$B$2:$B$478,$B17) -> 11355740 | D17: =SUMIFS(Cierres!$E$2:$E$478,Cierres!$A$2:$A$478,">="&DATE(2025,8,1),Cierres!$A$2:$A$478,"<="&EOMONTH(DATE(2025,8,1),0),Cierres!$B$2:$B$478,$B17) -> 7807500 | E17: =IF(C17=0,"",D17/C17) -> 0.68753776 | F17: =SUMIFS(Cierres!$K$2:$K$478,Cierres!$A$2:$A$478,">="&DATE(2025,8,1),Cierres!$A$2:$A$478,"<="&EOMONTH(DATE(2025,8,1),0),Cierres!$B$2:$B$478,$B17) -> 1082 | G17: =IF(F17=0,"",SUMIFS(Cierres!$J$2:$J$478,Cierres!$A$2:$A$478,">="&DATE(2025,8,1),Cierres!$A$2:$A$478,"<="&EOMONTH(DATE(2025,8,1),0),Cierres!$B$2:$B$478,$B17,Cierres!$K$2:$K$478,">0")/F17) -> 10495.139 | H17: =ROUND(SUMIFS(Cierres!$F$2:$F$478,Cierres!$A$2:$A$478,">="&DATE(2025,8,1),Cierres!$A$2:$A$478,"<="&EOMONTH(DATE(2025,8,1),0),Cierres!$B$2:$B$478,$B17)*Léeme!$B$13+SUMIFS(Cierres!$G$2:$G$478,Cierres!$A$2:$A$478,">="&DATE(2025,8,1),Cierres!$A$2:$A$478,"<="&EOMONTH(DATE(2025,8,1),0),Cierres!$B$2:$B$478,$B17)*Léeme!$B$14+SUMIFS(Cierres!$H$2:$H$478,Cierres!$A$2:$A$478,">="&DATE(2025,8,1),Cierres!$A$2:$A$478,"<="&EOMONTH(DATE(2025,8,1),0),Cierres!$B$2:$B$478,$B17)*Léeme!$B$15,0) -> 52825 | I17: =COUNTIFS(Cierres!$A$2:$A$478,">="&DATE(2025,8,1),Cierres!$A$2:$A$478,"<="&EOMONTH(DATE(2025,8,1),0),Cierres!$B$2:$B$478,$B17,Cierres!$Q$2:$Q$478,"<>") -> 24 | J17: =COUNTIFS(Cierres!$A$2:$A$478,">="&DATE(2025,8,1),Cierres!$A$2:$A$478,"<="&EOMONTH(DATE(2025,8,1),0),Cierres!$B$2:$B$478,$B17,Cierres!$S$2:$S$478,"Cuadra") -> 23 | K17: =IF(I17=0,"",J17/I17) -> 0.95833333 | L17: =-SUMIFS(Cierres!$R$2:$R$478,Cierres!$A$2:$A$478,">="&DATE(2025,8,1),Cierres!$A$2:$A$478,"<="&EOMONTH(DATE(2025,8,1),0),Cierres!$B$2:$B$478,$B17,Cierres!$R$2:$R$478,"<"&-Léeme!$B$12) -> 610
A18: 2025-09 | B18: Centro | C18: =SUMIFS(Cierres!$J$2:$J$478,Cierres!$A$2:$A$478,">="&DATE(2025,9,1),Cierres!$A$2:$A$478,"<="&EOMONTH(DATE(2025,9,1),0),Cierres!$B$2:$B$478,$B18) -> 15321760 | D18: =SUMIFS(Cierres!$E$2:$E$478,Cierres!$A$2:$A$478,">="&DATE(2025,9,1),Cierres!$A$2:$A$478,"<="&EOMONTH(DATE(2025,9,1),0),Cierres!$B$2:$B$478,$B18) -> 10222300 | E18: =IF(C18=0,"",D18/C18) -> 0.66717531 | F18: =SUMIFS(Cierres!$K$2:$K$478,Cierres!$A$2:$A$478,">="&DATE(2025,9,1),Cierres!$A$2:$A$478,"<="&EOMONTH(DATE(2025,9,1),0),Cierres!$B$2:$B$478,$B18) -> 1407 | G18: =IF(F18=0,"",SUMIFS(Cierres!$J$2:$J$478,Cierres!$A$2:$A$478,">="&DATE(2025,9,1),Cierres!$A$2:$A$478,"<="&EOMONTH(DATE(2025,9,1),0),Cierres!$B$2:$B$478,$B18,Cierres!$K$2:$K$478,">0")/F18) -> 10889.666 | H18: =ROUND(SUMIFS(Cierres!$F$2:$F$478,Cierres!$A$2:$A$478,">="&DATE(2025,9,1),Cierres!$A$2:$A$478,"<="&EOMONTH(DATE(2025,9,1),0),Cierres!$B$2:$B$478,$B18)*Léeme!$B$13+SUMIFS(Cierres!$G$2:$G$478,Cierres!$A$2:$A$478,">="&DATE(2025,9,1),Cierres!$A$2:$A$478,"<="&EOMONTH(DATE(2025,9,1),0),Cierres!$B$2:$B$478,$B18)*Léeme!$B$14+SUMIFS(Cierres!$H$2:$H$478,Cierres!$A$2:$A$478,">="&DATE(2025,9,1),Cierres!$A$2:$A$478,"<="&EOMONTH(DATE(2025,9,1),0),Cierres!$B$2:$B$478,$B18)*Léeme!$B$15,0) -> 75169 | I18: =COUNTIFS(Cierres!$A$2:$A$478,">="&DATE(2025,9,1),Cierres!$A$2:$A$478,"<="&EOMONTH(DATE(2025,9,1),0),Cierres!$B$2:$B$478,$B18,Cierres!$Q$2:$Q$478,"<>") -> 25 | J18: =COUNTIFS(Cierres!$A$2:$A$478,">="&DATE(2025,9,1),Cierres!$A$2:$A$478,"<="&EOMONTH(DATE(2025,9,1),0),Cierres!$B$2:$B$478,$B18,Cierres!$S$2:$S$478,"Cuadra") -> 14 | K18: =IF(I18=0,"",J18/I18) -> 0.56 | L18: =-SUMIFS(Cierres!$R$2:$R$478,Cierres!$A$2:$A$478,">="&DATE(2025,9,1),Cierres!$A$2:$A$478,"<="&EOMONTH(DATE(2025,9,1),0),Cierres!$B$2:$B$478,$B18,Cierres!$R$2:$R$478,"<"&-Léeme!$B$12) -> 40990
A19: 2025-09 | B19: Jardín | C19: =SUMIFS(Cierres!$J$2:$J$478,Cierres!$A$2:$A$478,">="&DATE(2025,9,1),Cierres!$A$2:$A$478,"<="&EOMONTH(DATE(2025,9,1),0),Cierres!$B$2:$B$478,$B19) -> 9568090 | D19: =SUMIFS(Cierres!$E$2:$E$478,Cierres!$A$2:$A$478,">="&DATE(2025,9,1),Cierres!$A$2:$A$478,"<="&EOMONTH(DATE(2025,9,1),0),Cierres!$B$2:$B$478,$B19) -> 6398570 | E19: =IF(C19=0,"",D19/C19) -> 0.66874057 | F19: =SUMIFS(Cierres!$K$2:$K$478,Cierres!$A$2:$A$478,">="&DATE(2025,9,1),Cierres!$A$2:$A$478,"<="&EOMONTH(DATE(2025,9,1),0),Cierres!$B$2:$B$478,$B19) -> 880 | G19: =IF(F19=0,"",SUMIFS(Cierres!$J$2:$J$478,Cierres!$A$2:$A$478,">="&DATE(2025,9,1),Cierres!$A$2:$A$478,"<="&EOMONTH(DATE(2025,9,1),0),Cierres!$B$2:$B$478,$B19,Cierres!$K$2:$K$478,">0")/F19) -> 10872.83 | H19: =ROUND(SUMIFS(Cierres!$F$2:$F$478,Cierres!$A$2:$A$478,">="&DATE(2025,9,1),Cierres!$A$2:$A$478,"<="&EOMONTH(DATE(2025,9,1),0),Cierres!$B$2:$B$478,$B19)*Léeme!$B$13+SUMIFS(Cierres!$G$2:$G$478,Cierres!$A$2:$A$478,">="&DATE(2025,9,1),Cierres!$A$2:$A$478,"<="&EOMONTH(DATE(2025,9,1),0),Cierres!$B$2:$B$478,$B19)*Léeme!$B$14+SUMIFS(Cierres!$H$2:$H$478,Cierres!$A$2:$A$478,">="&DATE(2025,9,1),Cierres!$A$2:$A$478,"<="&EOMONTH(DATE(2025,9,1),0),Cierres!$B$2:$B$478,$B19)*Léeme!$B$15,0) -> 47035 | I19: =COUNTIFS(Cierres!$A$2:$A$478,">="&DATE(2025,9,1),Cierres!$A$2:$A$478,"<="&EOMONTH(DATE(2025,9,1),0),Cierres!$B$2:$B$478,$B19,Cierres!$Q$2:$Q$478,"<>") -> 23 | J19: =COUNTIFS(Cierres!$A$2:$A$478,">="&DATE(2025,9,1),Cierres!$A$2:$A$478,"<="&EOMONTH(DATE(2025,9,1),0),Cierres!$B$2:$B$478,$B19,Cierres!$S$2:$S$478,"Cuadra") -> 19 | K19: =IF(I19=0,"",J19/I19) -> 0.82608696 | L19: =-SUMIFS(Cierres!$R$2:$R$478,Cierres!$A$2:$A$478,">="&DATE(2025,9,1),Cierres!$A$2:$A$478,"<="&EOMONTH(DATE(2025,9,1),0),Cierres!$B$2:$B$478,$B19,Cierres!$R$2:$R$478,"<"&-Léeme!$B$12) -> 1720
A20: 2025-10 | B20: Centro | C20: =SUMIFS(Cierres!$J$2:$J$478,Cierres!$A$2:$A$478,">="&DATE(2025,10,1),Cierres!$A$2:$A$478,"<="&EOMONTH(DATE(2025,10,1),0),Cierres!$B$2:$B$478,$B20) -> 4916270 | D20: =SUMIFS(Cierres!$E$2:$E$478,Cierres!$A$2:$A$478,">="&DATE(2025,10,1),Cierres!$A$2:$A$478,"<="&EOMONTH(DATE(2025,10,1),0),Cierres!$B$2:$B$478,$B20) -> 3282600 | E20: =IF(C20=0,"",D20/C20) -> 0.66770133 | F20: =SUMIFS(Cierres!$K$2:$K$478,Cierres!$A$2:$A$478,">="&DATE(2025,10,1),Cierres!$A$2:$A$478,"<="&EOMONTH(DATE(2025,10,1),0),Cierres!$B$2:$B$478,$B20) -> 440 | G20: =IF(F20=0,"",SUMIFS(Cierres!$J$2:$J$478,Cierres!$A$2:$A$478,">="&DATE(2025,10,1),Cierres!$A$2:$A$478,"<="&EOMONTH(DATE(2025,10,1),0),Cierres!$B$2:$B$478,$B20,Cierres!$K$2:$K$478,">0")/F20) -> 11173.341 | H20: =ROUND(SUMIFS(Cierres!$F$2:$F$478,Cierres!$A$2:$A$478,">="&DATE(2025,10,1),Cierres!$A$2:$A$478,"<="&EOMONTH(DATE(2025,10,1),0),Cierres!$B$2:$B$478,$B20)*Léeme!$B$13+SUMIFS(Cierres!$G$2:$G$478,Cierres!$A$2:$A$478,">="&DATE(2025,10,1),Cierres!$A$2:$A$478,"<="&EOMONTH(DATE(2025,10,1),0),Cierres!$B$2:$B$478,$B20)*Léeme!$B$14+SUMIFS(Cierres!$H$2:$H$478,Cierres!$A$2:$A$478,">="&DATE(2025,10,1),Cierres!$A$2:$A$478,"<="&EOMONTH(DATE(2025,10,1),0),Cierres!$B$2:$B$478,$B20)*Léeme!$B$15,0) -> 23890 | I20: =COUNTIFS(Cierres!$A$2:$A$478,">="&DATE(2025,10,1),Cierres!$A$2:$A$478,"<="&EOMONTH(DATE(2025,10,1),0),Cierres!$B$2:$B$478,$B20,Cierres!$Q$2:$Q$478,"<>") -> 8 | J20: =COUNTIFS(Cierres!$A$2:$A$478,">="&DATE(2025,10,1),Cierres!$A$2:$A$478,"<="&EOMONTH(DATE(2025,10,1),0),Cierres!$B$2:$B$478,$B20,Cierres!$S$2:$S$478,"Cuadra") -> 6 | K20: =IF(I20=0,"",J20/I20) -> 0.75 | L20: =-SUMIFS(Cierres!$R$2:$R$478,Cierres!$A$2:$A$478,">="&DATE(2025,10,1),Cierres!$A$2:$A$478,"<="&EOMONTH(DATE(2025,10,1),0),Cierres!$B$2:$B$478,$B20,Cierres!$R$2:$R$478,"<"&-Léeme!$B$12) -> 15100
A21: 2025-10 | B21: Jardín | C21: =SUMIFS(Cierres!$J$2:$J$478,Cierres!$A$2:$A$478,">="&DATE(2025,10,1),Cierres!$A$2:$A$478,"<="&EOMONTH(DATE(2025,10,1),0),Cierres!$B$2:$B$478,$B21) -> 3637310 | D21: =SUMIFS(Cierres!$E$2:$E$478,Cierres!$A$2:$A$478,">="&DATE(2025,10,1),Cierres!$A$2:$A$478,"<="&EOMONTH(DATE(2025,10,1),0),Cierres!$B$2:$B$478,$B21) -> 2402360 | E21: =IF(C21=0,"",D21/C21) -> 0.66047711 | F21: =SUMIFS(Cierres!$K$2:$K$478,Cierres!$A$2:$A$478,">="&DATE(2025,10,1),Cierres!$A$2:$A$478,"<="&EOMONTH(DATE(2025,10,1),0),Cierres!$B$2:$B$478,$B21) -> 321 | G21: =IF(F21=0,"",SUMIFS(Cierres!$J$2:$J$478,Cierres!$A$2:$A$478,">="&DATE(2025,10,1),Cierres!$A$2:$A$478,"<="&EOMONTH(DATE(2025,10,1),0),Cierres!$B$2:$B$478,$B21,Cierres!$K$2:$K$478,">0")/F21) -> 11331.184 | H21: =ROUND(SUMIFS(Cierres!$F$2:$F$478,Cierres!$A$2:$A$478,">="&DATE(2025,10,1),Cierres!$A$2:$A$478,"<="&EOMONTH(DATE(2025,10,1),0),Cierres!$B$2:$B$478,$B21)*Léeme!$B$13+SUMIFS(Cierres!$G$2:$G$478,Cierres!$A$2:$A$478,">="&DATE(2025,10,1),Cierres!$A$2:$A$478,"<="&EOMONTH(DATE(2025,10,1),0),Cierres!$B$2:$B$478,$B21)*Léeme!$B$14+SUMIFS(Cierres!$H$2:$H$478,Cierres!$A$2:$A$478,">="&DATE(2025,10,1),Cierres!$A$2:$A$478,"<="&EOMONTH(DATE(2025,10,1),0),Cierres!$B$2:$B$478,$B21)*Léeme!$B$15,0) -> 18085 | I21: =COUNTIFS(Cierres!$A$2:$A$478,">="&DATE(2025,10,1),Cierres!$A$2:$A$478,"<="&EOMONTH(DATE(2025,10,1),0),Cierres!$B$2:$B$478,$B21,Cierres!$Q$2:$Q$478,"<>") -> 8 | J21: =COUNTIFS(Cierres!$A$2:$A$478,">="&DATE(2025,10,1),Cierres!$A$2:$A$478,"<="&EOMONTH(DATE(2025,10,1),0),Cierres!$B$2:$B$478,$B21,Cierres!$S$2:$S$478,"Cuadra") -> 7 | K21: =IF(I21=0,"",J21/I21) -> 0.875 | L21: =-SUMIFS(Cierres!$R$2:$R$478,Cierres!$A$2:$A$478,">="&DATE(2025,10,1),Cierres!$A$2:$A$478,"<="&EOMONTH(DATE(2025,10,1),0),Cierres!$B$2:$B$478,$B21,Cierres!$R$2:$R$478,"<"&-Léeme!$B$12) -> 0
A23: Fórmulas sobre la hoja Cierres. Hasta mayo (Excel) no hay tickets ni arqueo; hasta marzo la billetera está dentro de transferencia.

Sheet Fiado
A1: Cliente | B1: Nombre | C1: Condición | D1: Comprado a cuenta | E1: Cobrado | F1: Saldo | G1: Saldo del motor | H1: Control | I1: Comprado a cuenta (90 d) | J1: Cobrado (90 d) | K1: Pagó de lo comprado | L1: Estado
A2: 1 | B2: Restaurante La Esquina | C2: Cuenta corriente | D2: =SUMIFS(Pedidos!$D$2:$D$732,Pedidos!$B$2:$B$732,A2,Pedidos!$E$2:$E$732,"Cuenta corriente") -> 3654800 | E2: =SUMIFS(Cobros!$D$2:$D$353,Cobros!$B$2:$B$353,A2) -> 3487700 | F2: =IF(D2=0,"",D2-E2) -> 167100 | G2: 167100 | H2: =IF(G2="","",IF(F2=G2,"OK","Revisar")) -> OK | I2: =SUMIFS(Pedidos!$D$2:$D$732,Pedidos!$B$2:$B$732,A2,Pedidos!$E$2:$E$732,"Cuenta corriente",Pedidos!$A$2:$A$732,">"&Léeme!$B$11-90) -> 1330700 | J2: =SUMIFS(Cobros!$D$2:$D$353,Cobros!$B$2:$B$353,A2,Cobros!$A$2:$A$353,">"&Léeme!$B$11-90) -> 1213000 | K2: =IF(I2=0,"",J2/I2) -> 0.91155031 | L2: Activo
A3: 2 | B3: Rotisería El Buen Gusto | C3: Contado | D3: =SUMIFS(Pedidos!$D$2:$D$732,Pedidos!$B$2:$B$732,A3,Pedidos!$E$2:$E$732,"Cuenta corriente") -> 0 | E3: =SUMIFS(Cobros!$D$2:$D$353,Cobros!$B$2:$B$353,A3) -> 1039700 | F3: =IF(D3=0,"",D3-E3) | H3: =IF(G3="","",IF(F3=G3,"OK","Revisar")) | I3: =SUMIFS(Pedidos!$D$2:$D$732,Pedidos!$B$2:$B$732,A3,Pedidos!$E$2:$E$732,"Cuenta corriente",Pedidos!$A$2:$A$732,">"&Léeme!$B$11-90) -> 0 | J3: =SUMIFS(Cobros!$D$2:$D$353,Cobros!$B$2:$B$353,A3,Cobros!$A$2:$A$353,">"&Léeme!$B$11-90) -> 725200 | K3: =IF(I3=0,"",J3/I3) | L3: Activo
A4: 3 | B4: Almacén Doña Rosa | C4: Cuenta corriente | D4: =SUMIFS(Pedidos!$D$2:$D$732,Pedidos!$B$2:$B$732,A4,Pedidos!$E$2:$E$732,"Cuenta corriente") -> 4064600 | E4: =SUMIFS(Cobros!$D$2:$D$353,Cobros!$B$2:$B$353,A4) -> 4007200 | F4: =IF(D4=0,"",D4-E4) -> 57400 | G4: 57400 | H4: =IF(G4="","",IF(F4=G4,"OK","Revisar")) -> OK | I4: =SUMIFS(Pedidos!$D$2:$D$732,Pedidos!$B$2:$B$732,A4,Pedidos!$E$2:$E$732,"Cuenta corriente",Pedidos!$A$2:$A$732,">"&Léeme!$B$11-90) -> 0 | J4: =SUMIFS(Cobros!$D$2:$D$353,Cobros!$B$2:$B$353,A4,Cobros!$A$2:$A$353,">"&Léeme!$B$11-90) -> 0 | K4: =IF(I4=0,"",J4/I4) | L4: Dejó de comprar
A5: 4 | B5: Bodegón Los Abuelos | C5: Cuenta corriente | D5: =SUMIFS(Pedidos!$D$2:$D$732,Pedidos!$B$2:$B$732,A5,Pedidos!$E$2:$E$732,"Cuenta corriente") -> 4973800 | E5: =SUMIFS(Cobros!$D$2:$D$353,Cobros!$B$2:$B$353,A5) -> 4645600 | F5: =IF(D5=0,"",D5-E5) -> 328200 | G5: 328200 | H5: =IF(G5="","",IF(F5=G5,"OK","Revisar")) -> OK | I5: =SUMIFS(Pedidos!$D$2:$D$732,Pedidos!$B$2:$B$732,A5,Pedidos!$E$2:$E$732,"Cuenta corriente",Pedidos!$A$2:$A$732,">"&Léeme!$B$11-90) -> 1627200 | J5: =SUMIFS(Cobros!$D$2:$D$353,Cobros!$B$2:$B$353,A5,Cobros!$A$2:$A$353,">"&Léeme!$B$11-90) -> 1718200 | K5: =IF(I5=0,"",J5/I5) -> 1.0559243 | L5: Activo
A6: 5 | B6: Cantina del Puerto | C6: Cuenta corriente | D6: =SUMIFS(Pedidos!$D$2:$D$732,Pedidos!$B$2:$B$732,A6,Pedidos!$E$2:$E$732,"Cuenta corriente") -> 5903900 | E6: =SUMIFS(Cobros!$D$2:$D$353,Cobros!$B$2:$B$353,A6) -> 5301900 | F6: =IF(D6=0,"",D6-E6) -> 602000 | G6: 602000 | H6: =IF(G6="","",IF(F6=G6,"OK","Revisar")) -> OK | I6: =SUMIFS(Pedidos!$D$2:$D$732,Pedidos!$B$2:$B$732,A6,Pedidos!$E$2:$E$732,"Cuenta corriente",Pedidos!$A$2:$A$732,">"&Léeme!$B$11-90) -> 2135600 | J6: =SUMIFS(Cobros!$D$2:$D$353,Cobros!$B$2:$B$353,A6,Cobros!$A$2:$A$353,">"&Léeme!$B$11-90) -> 1554500 | K6: =IF(I6=0,"",J6/I6) -> 0.72789848 | L6: Activo
A7: 6 | B7: Rotisería Sabores | C7: Cuenta corriente | D7: =SUMIFS(Pedidos!$D$2:$D$732,Pedidos!$B$2:$B$732,A7,Pedidos!$E$2:$E$732,"Cuenta corriente") -> 1516200 | E7: =SUMIFS(Cobros!$D$2:$D$353,Cobros!$B$2:$B$353,A7) -> 1501800 | F7: =IF(D7=0,"",D7-E7) -> 14400 | G7: 14400 | H7: =IF(G7="","",IF(F7=G7,"OK","Revisar")) -> OK | I7: =SUMIFS(Pedidos!$D$2:$D$732,Pedidos!$B$2:$B$732,A7,Pedidos!$E$2:$E$732,"Cuenta corriente",Pedidos!$A$2:$A$732,">"&Léeme!$B$11-90) -> 482200 | J7: =SUMIFS(Cobros!$D$2:$D$353,Cobros!$B$2:$B$353,A7,Cobros!$A$2:$A$353,">"&Léeme!$B$11-90) -> 475600 | K7: =IF(I7=0,"",J7/I7) -> 0.98631273 | L7: Compra menos seguido
A8: 7 | B8: Restaurante Il Forno | C8: Cuenta corriente | D8: =SUMIFS(Pedidos!$D$2:$D$732,Pedidos!$B$2:$B$732,A8,Pedidos!$E$2:$E$732,"Cuenta corriente") -> 1907400 | E8: =SUMIFS(Cobros!$D$2:$D$353,Cobros!$B$2:$B$353,A8) -> 1826200 | F8: =IF(D8=0,"",D8-E8) -> 81200 | G8: 81200 | H8: =IF(G8="","",IF(F8=G8,"OK","Revisar")) -> OK | I8: =SUMIFS(Pedidos!$D$2:$D$732,Pedidos!$B$2:$B$732,A8,Pedidos!$E$2:$E$732,"Cuenta corriente",Pedidos!$A$2:$A$732,">"&Léeme!$B$11-90) -> 692100 | J8: =SUMIFS(Cobros!$D$2:$D$353,Cobros!$B$2:$B$353,A8,Cobros!$A$2:$A$353,">"&Léeme!$B$11-90) -> 614100 | K8: =IF(I8=0,"",J8/I8) -> 0.88729952 | L8: Activo
A9: 8 | B9: Almacén San Martín | C9: Contado | D9: =SUMIFS(Pedidos!$D$2:$D$732,Pedidos!$B$2:$B$732,A9,Pedidos!$E$2:$E$732,"Cuenta corriente") -> 0 | E9: =SUMIFS(Cobros!$D$2:$D$353,Cobros!$B$2:$B$353,A9) -> 4703400 | F9: =IF(D9=0,"",D9-E9) | H9: =IF(G9="","",IF(F9=G9,"OK","Revisar")) | I9: =SUMIFS(Pedidos!$D$2:$D$732,Pedidos!$B$2:$B$732,A9,Pedidos!$E$2:$E$732,"Cuenta corriente",Pedidos!$A$2:$A$732,">"&Léeme!$B$11-90) -> 0 | J9: =SUMIFS(Cobros!$D$2:$D$353,Cobros!$B$2:$B$353,A9,Cobros!$A$2:$A$353,">"&Léeme!$B$11-90) -> 3475700 | K9: =IF(I9=0,"",J9/I9) | L9: Activo
A10: 9 | B10: Club Atlético Villa Sur | C10: Contado | D10: =SUMIFS(Pedidos!$D$2:$D$732,Pedidos!$B$2:$B$732,A10,Pedidos!$E$2:$E$732,"Cuenta corriente") -> 0 | E10: =SUMIFS(Cobros!$D$2:$D$353,Cobros!$B$2:$B$353,A10) -> 950100 | F10: =IF(D10=0,"",D10-E10) | H10: =IF(G10="","",IF(F10=G10,"OK","Revisar")) | I10: =SUMIFS(Pedidos!$D$2:$D$732,Pedidos!$B$2:$B$732,A10,Pedidos!$E$2:$E$732,"Cuenta corriente",Pedidos!$A$2:$A$732,">"&Léeme!$B$11-90) -> 0 | J10: =SUMIFS(Cobros!$D$2:$D$353,Cobros!$B$2:$B$353,A10,Cobros!$A$2:$A$353,">"&Léeme!$B$11-90) -> 660500 | K10: =IF(I10=0,"",J10/I10) | L10: Activo
A11: 10 | B11: Parrilla El Fogón | C11: Cuenta corriente | D11: =SUMIFS(Pedidos!$D$2:$D$732,Pedidos!$B$2:$B$732,A11,Pedidos!$E$2:$E$732,"Cuenta corriente") -> 1681300 | E11: =SUMIFS(Cobros!$D$2:$D$353,Cobros!$B$2:$B$353,A11) -> 1529400 | F11: =IF(D11=0,"",D11-E11) -> 151900 | G11: 151900 | H11: =IF(G11="","",IF(F11=G11,"OK","Revisar")) -> OK | I11: =SUMIFS(Pedidos!$D$2:$D$732,Pedidos!$B$2:$B$732,A11,Pedidos!$E$2:$E$732,"Cuenta corriente",Pedidos!$A$2:$A$732,">"&Léeme!$B$11-90) -> 206000 | J11: =SUMIFS(Cobros!$D$2:$D$353,Cobros!$B$2:$B$353,A11,Cobros!$A$2:$A$353,">"&Léeme!$B$11-90) -> 213900 | K11: =IF(I11=0,"",J11/I11) -> 1.0383495 | L11: Dejó de comprar
A12: 11 | B12: Bar La Plaza | C12: Contado | D12: =SUMIFS(Pedidos!$D$2:$D$732,Pedidos!$B$2:$B$732,A12,Pedidos!$E$2:$E$732,"Cuenta corriente") -> 0 | E12: =SUMIFS(Cobros!$D$2:$D$353,Cobros!$B$2:$B$353,A12) -> 2368400 | F12: =IF(D12=0,"",D12-E12) | H12: =IF(G12="","",IF(F12=G12,"OK","Revisar")) | I12: =SUMIFS(Pedidos!$D$2:$D$732,Pedidos!$B$2:$B$732,A12,Pedidos!$E$2:$E$732,"Cuenta corriente",Pedidos!$A$2:$A$732,">"&Léeme!$B$11-90) -> 0 | J12: =SUMIFS(Cobros!$D$2:$D$353,Cobros!$B$2:$B$353,A12,Cobros!$A$2:$A$353,">"&Léeme!$B$11-90) -> 1726000 | K12: =IF(I12=0,"",J12/I12) | L12: Activo
A13: 12 | B13: Rotisería La Nonna | C13: Contado | D13: =SUMIFS(Pedidos!$D$2:$D$732,Pedidos!$B$2:$B$732,A13,Pedidos!$E$2:$E$732,"Cuenta corriente") -> 0 | E13: =SUMIFS(Cobros!$D$2:$D$353,Cobros!$B$2:$B$353,A13) -> 1417200 | F13: =IF(D13=0,"",D13-E13) | H13: =IF(G13="","",IF(F13=G13,"OK","Revisar")) | I13: =SUMIFS(Pedidos!$D$2:$D$732,Pedidos!$B$2:$B$732,A13,Pedidos!$E$2:$E$732,"Cuenta corriente",Pedidos!$A$2:$A$732,">"&Léeme!$B$11-90) -> 0 | J13: =SUMIFS(Cobros!$D$2:$D$353,Cobros!$B$2:$B$353,A13,Cobros!$A$2:$A$353,">"&Léeme!$B$11-90) -> 1142800 | K13: =IF(I13=0,"",J13/I13) | L13: Activo
A14: 13 | B14: Restaurante Mediterráneo | C14: Cuenta corriente | D14: =SUMIFS(Pedidos!$D$2:$D$732,Pedidos!$B$2:$B$732,A14,Pedidos!$E$2:$E$732,"Cuenta corriente") -> 1448200 | E14: =SUMIFS(Cobros!$D$2:$D$353,Cobros!$B$2:$B$353,A14) -> 1187700 | F14: =IF(D14=0,"",D14-E14) -> 260500 | G14: 260500 | H14: =IF(G14="","",IF(F14=G14,"OK","Revisar")) -> OK | I14: =SUMIFS(Pedidos!$D$2:$D$732,Pedidos!$B$2:$B$732,A14,Pedidos!$E$2:$E$732,"Cuenta corriente",Pedidos!$A$2:$A$732,">"&Léeme!$B$11-90) -> 556900 | J14: =SUMIFS(Cobros!$D$2:$D$353,Cobros!$B$2:$B$353,A14,Cobros!$A$2:$A$353,">"&Léeme!$B$11-90) -> 349400 | K14: =IF(I14=0,"",J14/I14) -> 0.62740169 | L14: Activo · paga menos
A15: 14 | B15: Almacén El Trébol | C15: Cuenta corriente | D15: =SUMIFS(Pedidos!$D$2:$D$732,Pedidos!$B$2:$B$732,A15,Pedidos!$E$2:$E$732,"Cuenta corriente") -> 3867000 | E15: =SUMIFS(Cobros!$D$2:$D$353,Cobros!$B$2:$B$353,A15) -> 3654000 | F15: =IF(D15=0,"",D15-E15) -> 213000 | G15: 213000 | H15: =IF(G15="","",IF(F15=G15,"OK","Revisar")) -> OK | I15: =SUMIFS(Pedidos!$D$2:$D$732,Pedidos!$B$2:$B$732,A15,Pedidos!$E$2:$E$732,"Cuenta corriente",Pedidos!$A$2:$A$732,">"&Léeme!$B$11-90) -> 1220300 | J15: =SUMIFS(Cobros!$D$2:$D$353,Cobros!$B$2:$B$353,A15,Cobros!$A$2:$A$353,">"&Léeme!$B$11-90) -> 1301200 | K15: =IF(I15=0,"",J15/I15) -> 1.0662952 | L15: Activo
A16: 15 | B16: Comedor Escolar Norte | C16: Cuenta corriente | D16: =SUMIFS(Pedidos!$D$2:$D$732,Pedidos!$B$2:$B$732,A16,Pedidos!$E$2:$E$732,"Cuenta corriente") -> 5105800 | E16: =SUMIFS(Cobros!$D$2:$D$353,Cobros!$B$2:$B$353,A16) -> 4929400 | F16: =IF(D16=0,"",D16-E16) -> 176400 | G16: 176400 | H16: =IF(G16="","",IF(F16=G16,"OK","Revisar")) -> OK | I16: =SUMIFS(Pedidos!$D$2:$D$732,Pedidos!$B$2:$B$732,A16,Pedidos!$E$2:$E$732,"Cuenta corriente",Pedidos!$A$2:$A$732,">"&Léeme!$B$11-90) -> 1725000 | J16: =SUMIFS(Cobros!$D$2:$D$353,Cobros!$B$2:$B$353,A16,Cobros!$A$2:$A$353,">"&Léeme!$B$11-90) -> 1689600 | K16: =IF(I16=0,"",J16/I16) -> 0.97947826 | L16: Activo
A17: 16 | B17: Trattoria Bella Vista | C17: Contado | D17: =SUMIFS(Pedidos!$D$2:$D$732,Pedidos!$B$2:$B$732,A17,Pedidos!$E$2:$E$732,"Cuenta corriente") -> 0 | E17: =SUMIFS(Cobros!$D$2:$D$353,Cobros!$B$2:$B$353,A17) -> 1578000 | F17: =IF(D17=0,"",D17-E17) | H17: =IF(G17="","",IF(F17=G17,"OK","Revisar")) | I17: =SUMIFS(Pedidos!$D$2:$D$732,Pedidos!$B$2:$B$732,A17,Pedidos!$E$2:$E$732,"Cuenta corriente",Pedidos!$A$2:$A$732,">"&Léeme!$B$11-90) -> 0 | J17: =SUMIFS(Cobros!$D$2:$D$353,Cobros!$B$2:$B$353,A17,Cobros!$A$2:$A$353,">"&Léeme!$B$11-90) -> 1091500 | K17: =IF(I17=0,"",J17/I17) | L17: Activo
A18: 17 | B18: Rotisería Don Pepe | C18: Cuenta corriente | D18: =SUMIFS(Pedidos!$D$2:$D$732,Pedidos!$B$2:$B$732,A18,Pedidos!$E$2:$E$732,"Cuenta corriente") -> 1691500 | E18: =SUMIFS(Cobros!$D$2:$D$353,Cobros!$B$2:$B$353,A18) -> 1562400 | F18: =IF(D18=0,"",D18-E18) -> 129100 | G18: 129100 | H18: =IF(G18="","",IF(F18=G18,"OK","Revisar")) -> OK | I18: =SUMIFS(Pedidos!$D$2:$D$732,Pedidos!$B$2:$B$732,A18,Pedidos!$E$2:$E$732,"Cuenta corriente",Pedidos!$A$2:$A$732,">"&Léeme!$B$11-90) -> 329900 | J18: =SUMIFS(Cobros!$D$2:$D$353,Cobros!$B$2:$B$353,A18,Cobros!$A$2:$A$353,">"&Léeme!$B$11-90) -> 343200 | K18: =IF(I18=0,"",J18/I18) -> 1.0403152 | L18: Dejó de comprar
A19: 18 | B19: Restaurante Las Tinajas | C19: Contado | D19: =SUMIFS(Pedidos!$D$2:$D$732,Pedidos!$B$2:$B$732,A19,Pedidos!$E$2:$E$732,"Cuenta corriente") -> 0 | E19: =SUMIFS(Cobros!$D$2:$D$353,Cobros!$B$2:$B$353,A19) -> 1334400 | F19: =IF(D19=0,"",D19-E19) | H19: =IF(G19="","",IF(F19=G19,"OK","Revisar")) | I19: =SUMIFS(Pedidos!$D$2:$D$732,Pedidos!$B$2:$B$732,A19,Pedidos!$E$2:$E$732,"Cuenta corriente",Pedidos!$A$2:$A$732,">"&Léeme!$B$11-90) -> 0 | J19: =SUMIFS(Cobros!$D$2:$D$353,Cobros!$B$2:$B$353,A19,Cobros!$A$2:$A$353,">"&Léeme!$B$11-90) -> 1019400 | K19: =IF(I19=0,"",J19/I19) | L19: Activo
A20: 19 | B20: Bar del Centro | C20: Cuenta corriente | D20: =SUMIFS(Pedidos!$D$2:$D$732,Pedidos!$B$2:$B$732,A20,Pedidos!$E$2:$E$732,"Cuenta corriente") -> 7778500 | E20: =SUMIFS(Cobros!$D$2:$D$353,Cobros!$B$2:$B$353,A20) -> 7654600 | F20: =IF(D20=0,"",D20-E20) -> 123900 | G20: 123900 | H20: =IF(G20="","",IF(F20=G20,"OK","Revisar")) -> OK | I20: =SUMIFS(Pedidos!$D$2:$D$732,Pedidos!$B$2:$B$732,A20,Pedidos!$E$2:$E$732,"Cuenta corriente",Pedidos!$A$2:$A$732,">"&Léeme!$B$11-90) -> 3007700 | J20: =SUMIFS(Cobros!$D$2:$D$353,Cobros!$B$2:$B$353,A20,Cobros!$A$2:$A$353,">"&Léeme!$B$11-90) -> 2996700 | K20: =IF(I20=0,"",J20/I20) -> 0.99634272 | L20: Activo
A21: 20 | B21: Almacén Los Pinos | C21: Cuenta corriente | D21: =SUMIFS(Pedidos!$D$2:$D$732,Pedidos!$B$2:$B$732,A21,Pedidos!$E$2:$E$732,"Cuenta corriente") -> 4802500 | E21: =SUMIFS(Cobros!$D$2:$D$353,Cobros!$B$2:$B$353,A21) -> 4624400 | F21: =IF(D21=0,"",D21-E21) -> 178100 | G21: 178100 | H21: =IF(G21="","",IF(F21=G21,"OK","Revisar")) -> OK | I21: =SUMIFS(Pedidos!$D$2:$D$732,Pedidos!$B$2:$B$732,A21,Pedidos!$E$2:$E$732,"Cuenta corriente",Pedidos!$A$2:$A$732,">"&Léeme!$B$11-90) -> 1420000 | J21: =SUMIFS(Cobros!$D$2:$D$353,Cobros!$B$2:$B$353,A21,Cobros!$A$2:$A$353,">"&Léeme!$B$11-90) -> 1460400 | K21: =IF(I21=0,"",J21/I21) -> 1.0284507 | L21: Activo
A22: 21 | B22: Restaurante Tierra Nuestra | C22: Cuenta corriente | D22: =SUMIFS(Pedidos!$D$2:$D$732,Pedidos!$B$2:$B$732,A22,Pedidos!$E$2:$E$732,"Cuenta corriente") -> 2769700 | E22: =SUMIFS(Cobros!$D$2:$D$353,Cobros!$B$2:$B$353,A22) -> 2769100 | F22: =IF(D22=0,"",D22-E22) -> 600 | G22: 600 | H22: =IF(G22="","",IF(F22=G22,"OK","Revisar")) -> OK | I22: =SUMIFS(Pedidos!$D$2:$D$732,Pedidos!$B$2:$B$732,A22,Pedidos!$E$2:$E$732,"Cuenta corriente",Pedidos!$A$2:$A$732,">"&Léeme!$B$11-90) -> 857300 | J22: =SUMIFS(Cobros!$D$2:$D$353,Cobros!$B$2:$B$353,A22,Cobros!$A$2:$A$353,">"&Léeme!$B$11-90) -> 880500 | K22: =IF(I22=0,"",J22/I22) -> 1.0270617 | L22: En riesgo
A23: 22 | B23: Rotisería La Familia | C23: Contado | D23: =SUMIFS(Pedidos!$D$2:$D$732,Pedidos!$B$2:$B$732,A23,Pedidos!$E$2:$E$732,"Cuenta corriente") -> 0 | E23: =SUMIFS(Cobros!$D$2:$D$353,Cobros!$B$2:$B$353,A23) -> 4820600 | F23: =IF(D23=0,"",D23-E23) | H23: =IF(G23="","",IF(F23=G23,"OK","Revisar")) | I23: =SUMIFS(Pedidos!$D$2:$D$732,Pedidos!$B$2:$B$732,A23,Pedidos!$E$2:$E$732,"Cuenta corriente",Pedidos!$A$2:$A$732,">"&Léeme!$B$11-90) -> 0 | J23: =SUMIFS(Cobros!$D$2:$D$353,Cobros!$B$2:$B$353,A23,Cobros!$A$2:$A$353,">"&Léeme!$B$11-90) -> 3412700 | K23: =IF(I23=0,"",J23/I23) | L23: Activo
A24: 23 | B24: Hotel Cerro Azul | C24: Contado | D24: =SUMIFS(Pedidos!$D$2:$D$732,Pedidos!$B$2:$B$732,A24,Pedidos!$E$2:$E$732,"Cuenta corriente") -> 0 | E24: =SUMIFS(Cobros!$D$2:$D$353,Cobros!$B$2:$B$353,A24) -> 2650100 | F24: =IF(D24=0,"",D24-E24) | H24: =IF(G24="","",IF(F24=G24,"OK","Revisar")) | I24: =SUMIFS(Pedidos!$D$2:$D$732,Pedidos!$B$2:$B$732,A24,Pedidos!$E$2:$E$732,"Cuenta corriente",Pedidos!$A$2:$A$732,">"&Léeme!$B$11-90) -> 0 | J24: =SUMIFS(Cobros!$D$2:$D$353,Cobros!$B$2:$B$353,A24,Cobros!$A$2:$A$353,">"&Léeme!$B$11-90) -> 1917100 | K24: =IF(I24=0,"",J24/I24) | L24: Activo
A25: 24 | B25: Restaurante El Molino | C25: Cuenta corriente | D25: =SUMIFS(Pedidos!$D$2:$D$732,Pedidos!$B$2:$B$732,A25,Pedidos!$E$2:$E$732,"Cuenta corriente") -> 956100 | E25: =SUMIFS(Cobros!$D$2:$D$353,Cobros!$B$2:$B$353,A25) -> 767000 | F25: =IF(D25=0,"",D25-E25) -> 189100 | G25: 189100 | H25: =IF(G25="","",IF(F25=G25,"OK","Revisar")) -> OK | I25: =SUMIFS(Pedidos!$D$2:$D$732,Pedidos!$B$2:$B$732,A25,Pedidos!$E$2:$E$732,"Cuenta corriente",Pedidos!$A$2:$A$732,">"&Léeme!$B$11-90) -> 956100 | J25: =SUMIFS(Cobros!$D$2:$D$353,Cobros!$B$2:$B$353,A25,Cobros!$A$2:$A$353,">"&Léeme!$B$11-90) -> 767000 | K25: =IF(I25=0,"",J25/I25) -> 0.80221734 | L25: Nuevo

Sheet Cierres
A1: Fecha | B1: Local | C1: Responsable | D1: Fuente | E1: Efectivo | F1: Débito | G1: Crédito | H1: Billetera virtual | I1: Transferencia | J1: Venta total | K1: Tickets | L1: Gasto con la caja | M1: Concepto | N1: Retiro del dueño | O1: Fondo | P1: Efectivo esperado | Q1: Efectivo contado | R1: Diferencia | S1: Caja | T1: Incompleta
A2: 45659 | B2: Centro | D2: Excel | E2: 290670 | F2: 35160 | G2: 14700 | H2: 0 | I2: 19770 | J2: =SUM(E2:I2) -> 360300 | L2: 0 | N2: 256000 | P2: =IF(O2="","",O2+E2-L2-N2) | R2: =IF(OR(Q2="",P2=""),"",Q2-P2) | S2: =IF(R2="","",IF(ABS(R2)<=Léeme!$B$12,"Cuadra",IF(R2<0,"Faltante","Sobrante"))) | T2: No
A3: 45659 | B3: Jardín | D3: Excel | E3: 212420 | F3: 26850 | G3: 9720 | H3: 0 | I3: 15960 | J3: =SUM(E3:I3) -> 264950 | L3: 0 | N3: 0 | P3: =IF(O3="","",O3+E3-L3-N3) | R3: =IF(OR(Q3="",P3=""),"",Q3-P3) | S3: =IF(R3="","",IF(ABS(R3)<=Léeme!$B$12,"Cuadra",IF(R3<0,"Faltante","Sobrante"))) | T3: No
A4: 45660 | B4: Centro | D4: Excel | E4: 262960 | F4: 34000 | G4: 12360 | H4: 0 | I4: 21370 | J4: =SUM(E4:I4) -> 330690 | L4: 12950 | M4: Envases | N4: 0 | P4: =IF(O4="","",O4+E4-L4-N4) | R4: =IF(OR(Q4="",P4=""),"",Q4-P4) | S4: =IF(R4="","",IF(ABS(R4)<=Léeme!$B$12,"Cuadra",IF(R4<0,"Faltante","Sobrante"))) | T4: No
A5: 45660 | B5: Jardín | D5: Excel | E5: 204580 | F5: 27510 | G5: 10270 | H5: 0 | I5: 16660 | J5: =SUM(E5:I5) -> 259020 | L5: 0 | N5: 124000 | P5: =IF(O5="","",O5+E5-L5-N5) | R5: =IF(OR(Q5="",P5=""),"",Q5-P5) | S5: =IF(R5="","",IF(ABS(R5)<=Léeme!$B$12,"Cuadra",IF(R5<0,"Faltante","Sobrante"))) | T5: No
A6: 45661 | B6: Centro | D6: Excel | E6: 368810 | F6: 47260 | G6: 18230 | H6: 0 | I6: 28590 | J6: =SUM(E6:I6) -> 462890 | L6: 8100 | M6: Verdulería | N6: 0 | P6: =IF(O6="","",O6+E6-L6-N6) | R6: =IF(OR(Q6="",P6=""),"",Q6-P6) | S6: =IF(R6="","",IF(ABS(R6)<=Léeme!$B$12,"Cuadra",IF(R6<0,"Faltante","Sobrante"))) | T6: No
A7: 45661 | B7: Jardín | D7: Excel | E7: 331140 | F7: 44530 | G7: 15270 | H7: 0 | I7: 23160 | J7: =SUM(E7:I7) -> 414100 | L7: 3280 | M7: Limpieza | N7: 206000 | P7: =IF(O7="","",O7+E7-L7-N7) | R7: =IF(OR(Q7="",P7=""),"",Q7-P7) | S7: =IF(R7="","",IF(ABS(R7)<=Léeme!$B$12,"Cuadra",IF(R7<0,"Faltante","Sobrante"))) | T7: No
A8: 45662 | B8: Centro | D8: Excel | E8: 646200 | F8: 81120 | G8: 29660 | H8: 0 | I8: 47210 | J8: =SUM(E8:I8) -> 804190 | L8: 0 | N8: 497000 | P8: =IF(O8="","",O8+E8-L8-N8) | R8: =IF(OR(Q8="",P8=""),"",Q8-P8) | S8: =IF(R8="","",IF(ABS(R8)<=Léeme!$B$12,"Cuadra",IF(R8<0,"Faltante","Sobrante"))) | T8: No
A9: 45662 | B9: Jardín | D9: Excel | E9: 511510 | F9: 57830 | G9: 24240 | H9: 0 | I9: 37710 | J9: =SUM(E9:I9) -> 631290 | L9: 0 | N9: 447000 | P9: =IF(O9="","",O9+E9-L9-N9) | R9: =IF(OR(Q9="",P9=""),"",Q9-P9) | S9: =IF(R9="","",IF(ABS(R9)<=Léeme!$B$12,"Cuadra",IF(R9<0,"Faltante","Sobrante"))) | T9: No
A10: 45664 | B10: Centro | D10: Excel | E10: 241600 | F10: 32140 | G10: 13090 | H10: 0 | I10: 19450 | J10: =SUM(E10:I10) -> 306280 | L10: 14640 | M10: Verdulería | N10: 0 | P10: =IF(O10="","",O10+E10-L10-N10) | R10: =IF(OR(Q10="",P10=""),"",Q10-P10) | S10: =IF(R10="","",IF(ABS(R10)<=Léeme!$B$12,"Cuadra",IF(R10<0,"Faltante","Sobrante"))) | T10: No
A11: 45664 | B11: Jardín | D11: Excel | E11: 191030 | F11: 22630 | G11: 10000 | H11: 0 | I11: 15670 | J11: =SUM(E11:I11) -> 239330 | L11: 0 | N11: 0 | P11: =IF(O11="","",O11+E11-L11-N11) | R11: =IF(OR(Q11="",P11=""),"",Q11-P11) | S11: =IF(R11="","",IF(ABS(R11)<=Léeme!$B$12,"Cuadra",IF(R11<0,"Faltante","Sobrante"))) | T11: No
A12: 45665 | B12: Centro | D12: Excel | E12: 240450 | F12: 30530 | G12: 12110 | H12: 0 | I12: 17810 | J12: =SUM(E12:I12) -> 300900 | L12: 0 | N12: 211000 | P12: =IF(O12="","",O12+E12-L12-N12) | R12: =IF(OR(Q12="",P12=""),"",Q12-P12) | S12: =IF(R12="","",IF(ABS(R12)<=Léeme!$B$12,"Cuadra",IF(R12<0,"Faltante","Sobrante"))) | T12: No
A13: 45665 | B13: Jardín | D13: Excel | E13: 209810 | F13: 25630 | G13: 12380 | H13: 0 | I13: 16960 | J13: =SUM(E13:I13) -> 264780 | L13: 10070 | M13: Verdulería | N13: 161000 | P13: =IF(O13="","",O13+E13-L13-N13) | R13: =IF(OR(Q13="",P13=""),"",Q13-P13) | S13: =IF(R13="","",IF(ABS(R13)<=Léeme!$B$12,"Cuadra",IF(R13<0,"Faltante","Sobrante"))) | T13: No
A14: 45666 | B14: Centro | D14: Excel | E14: 289890 | F14: 31670 | G14: 13090 | H14: 0 | I14: 19650 | J14: =SUM(E14:I14) -> 354300 | L14: 0 | N14: 0 | P14: =IF(O14="","",O14+E14-L14-N14) | R14: =IF(OR(Q14="",P14=""),"",Q14-P14) | S14: =IF(R14="","",IF(ABS(R14)<=Léeme!$B$12,"Cuadra",IF(R14<0,"Faltante","Sobrante"))) | T14: No
A15: 45666 | B15: Jardín | D15: Excel | E15: 179760 | F15: 24280 | G15: 8980 | H15: 0 | I15: 14560 | J15: =SUM(E15:I15) -> 227580 | L15: 0 | N15: 139000 | P15: =IF(O15="","",O15+E15-L15-N15) | R15: =IF(OR(Q15="",P15=""),"",Q15-P15) | S15: =IF(R15="","",IF(ABS(R15)<=Léeme!$B$12,"Cuadra",IF(R15<0,"Faltante","Sobrante"))) | T15: No
A16: 45667 | B16: Centro | D16: Excel | E16: 266560 | F16: 40430 | G16: 15140 | H16: 0 | I16: 22700 | J16: =SUM(E16:I16) -> 344830 | L16: 17140 | M16: Verdulería | N16: 163000 | P16: =IF(O16="","",O16+E16-L16-N16) | R16: =IF(OR(Q16="",P16=""),"",Q16-P16) | S16: =IF(R16="","",IF(ABS(R16)<=Léeme!$B$12,"Cuadra",IF(R16<0,"Faltante","Sobrante"))) | T16: No
A17: 45667 | B17: Jardín | D17: Excel | E17: 182400 | F17: 21950 | G17: 9940 | H17: 0 | I17: 15230 | J17: =SUM(E17:I17) -> 229520 | L17: 0 | N17: 0 | P17: =IF(O17="","",O17+E17-L17-N17) | R17: =IF(OR(Q17="",P17=""),"",Q17-P17) | S17: =IF(R17="","",IF(ABS(R17)<=Léeme!$B$12,"Cuadra",IF(R17<0,"Faltante","Sobrante"))) | T17: No
A18: 45668 | B18: Centro | D18: Excel | E18: 398510 | F18: 46380 | G18: 18240 | H18: 0 | I18: 27930 | J18: =SUM(E18:I18) -> 491060 | L18: 5960 | M18: Delivery | N18: 0 | P18: =IF(O18="","",O18+E18-L18-N18) | R18: =IF(OR(Q18="",P18=""),"",Q18-P18) | S18: =IF(R18="","",IF(ABS(R18)<=Léeme!$B$12,"Cuadra",IF(R18<0,"Faltante","Sobrante"))) | T18: No
A19: 45668 | B19: Jardín | D19: Excel | E19: 310450 | F19: 38210 | G19: 18040 | H19: 0 | I19: 26930 | J19: =SUM(E19:I19) -> 393630 | L19: 0 | N19: 266000 | P19: =IF(O19="","",O19+E19-L19-N19) | R19: =IF(OR(Q19="",P19=""),"",Q19-P19) | S19: =IF(R19="","",IF(ABS(R19)<=Léeme!$B$12,"Cuadra",IF(R19<0,"Faltante","Sobrante"))) | T19: No
A20: 45669 | B20: Centro | D20: Excel | E20: 627890 | F20: 89190 | G20: 35420 | H20: 0 | I20: 55850 | J20: =SUM(E20:I20) -> 808350 | L20: 0 | N20: 0 | P20: =IF(O20="","",O20+E20-L20-N20) | R20: =IF(OR(Q20="",P20=""),"",Q20-P20) | S20: =IF(R20="","",IF(ABS(R20)<=Léeme!$B$12,"Cuadra",IF(R20<0,"Faltante","Sobrante"))) | T20: No
A21: 45669 | B21: Jardín | D21: Excel | E21: 503080 | F21: 60000 | G21: 23300 | H21: 0 | I21: 36330 | J21: =SUM(E21:I21) -> 622710 | L21: 0 | N21: 438000 | P21: =IF(O21="","",O21+E21-L21-N21) | R21: =IF(OR(Q21="",P21=""),"",Q21-P21) | S21: =IF(R21="","",IF(ABS(R21)<=Léeme!$B$12,"Cuadra",IF(R21<0,"Faltante","Sobrante"))) | T21: No
A22: 45671 | B22: Centro | D22: Excel | E22: 241450 | F22: 30380 | G22: 12680 | H22: 0 | I22: 20030 | J22: =SUM(E22:I22) -> 304540 | L22: 0 | N22: 0 | P22: =IF(O22="","",O22+E22-L22-N22) | R22: =IF(OR(Q22="",P22=""),"",Q22-P22) | S22: =IF(R22="","",IF(ABS(R22)<=Léeme!$B$12,"Cuadra",IF(R22<0,"Faltante","Sobrante"))) | T22: No
A23: 45671 | B23: Jardín | D23: Excel | E23: 193000 | F23: 28630 | G23: 10040 | H23: 0 | I23: 16950 | J23: =SUM(E23:I23) -> 248620 | L23: 0 | N23: 0 | P23: =IF(O23="","",O23+E23-L23-N23) | R23: =IF(OR(Q23="",P23=""),"",Q23-P23) | S23: =IF(R23="","",IF(ABS(R23)<=Léeme!$B$12,"Cuadra",IF(R23<0,"Faltante","Sobrante"))) | T23: No
A24: 45672 | B24: Centro | D24: Excel | E24: 237810 | F24: 32270 | G24: 13040 | H24: 0 | I24: 21650 | J24: =SUM(E24:I24) -> 304770 | L24: 13560 | M24: Verdulería | N24: 0 | P24: =IF(O24="","",O24+E24-L24-N24) | R24: =IF(OR(Q24="",P24=""),"",Q24-P24) | S24: =IF(R24="","",IF(ABS(R24)<=Léeme!$B$12,"Cuadra",IF(R24<0,"Faltante","Sobrante"))) | T24: No
A25: 45672 | B25: Jardín | D25: Excel | E25: 215090 | F25: 27670 | G25: 10760 | H25: 0 | I25: 17760 | J25: =SUM(E25:I25) -> 271280 | L25: 0 | N25: 0 | P25: =IF(O25="","",O25+E25-L25-N25) | R25: =IF(OR(Q25="",P25=""),"",Q25-P25) | S25: =IF(R25="","",IF(ABS(R25)<=Léeme!$B$12,"Cuadra",IF(R25<0,"Faltante","Sobrante"))) | T25: No
A26: 45673 | B26: Centro | D26: Excel | E26: 278620 | F26: 31090 | G26: 14750 | H26: 0 | I26: 21760 | J26: =SUM(E26:I26) -> 346220 | L26: 0 | N26: 0 | P26: =IF(O26="","",O26+E26-L26-N26) | R26: =IF(OR(Q26="",P26=""),"",Q26-P26) | S26: =IF(R26="","",IF(ABS(R26)<=Léeme!$B$12,"Cuadra",IF(R26<0,"Faltante","Sobrante"))) | T26: No
A27: 45673 | B27: Jardín | D27: Excel | E27: 204230 | F27: 25770 | G27: 10020 | H27: 0 | I27: 15330 | J27: =SUM(E27:I27) -> 255350 | L27: 3940 | M27: Delivery | N27: 0 | P27: =IF(O27="","",O27+E27-L27-N27) | R27: =IF(OR(Q27="",P27=""),"",Q27-P27) | S27: =IF(R27="","",IF(ABS(R27)<=Léeme!$B$12,"Cuadra",IF(R27<0,"Faltante","Sobrante"))) | T27: No
A28: 45674 | B28: Centro | D28: Excel | E28: 262370 | F28: 32630 | G28: 12910 | H28: 0 | I28: 19820 | J28: =SUM(E28:I28) -> 327730 | L28: 17250 | M28: Verdulería | N28: 0 | P28: =IF(O28="","",O28+E28-L28-N28) | R28: =IF(OR(Q28="",P28=""),"",Q28-P28) | S28: =IF(R28="","",IF(ABS(R28)<=Léeme!$B$12,"Cuadra",IF(R28<0,"Faltante","Sobrante"))) | T28: No
A29: 45674 | B29: Jardín | D29: Excel | E29: 190930 | F29: 25380 | G29: 10640 | H29: 0 | I29: 14170 | J29: =SUM(E29:I29) -> 241120 | L29: 10610 | M29: Verdulería | N29: 0 | P29: =IF(O29="","",O29+E29-L29-N29) | R29: =IF(OR(Q29="",P29=""),"",Q29-P29) | S29: =IF(R29="","",IF(ABS(R29)<=Léeme!$B$12,"Cuadra",IF(R29<0,"Faltante","Sobrante"))) | T29: No
A30: 45675 | B30: Centro | D30: Excel | E30: 421020 | F30: 52300 | G30: 18660 | H30: 0 | I30: 32660 | J30: =SUM(E30:I30) -> 524640 | L30: 0 | N30: 0 | P30: =IF(O30="","",O30+E30-L30-N30) | R30: =IF(OR(Q30="",P30=""),"",Q30-P30) | S30: =IF(R30="","",IF(ABS(R30)<=Léeme!$B$12,"Cuadra",IF(R30<0,"Faltante","Sobrante"))) | T30: No
A31: 45675 | B31: Jardín | D31: Excel | E31: 310530 | F31: 40050 | G31: 19360 | H31: 0 | I31: 28630 | J31: =SUM(E31:I31) -> 398570 | L31: 0 | N31: 254000 | P31: =IF(O31="","",O31+E31-L31-N31) | R31: =IF(OR(Q31="",P31=""),"",Q31-P31) | S31: =IF(R31="","",IF(ABS(R31)<=Léeme!$B$12,"Cuadra",IF(R31<0,"Faltante","Sobrante"))) | T31: No
A32: 45676 | B32: Centro | D32: Excel | E32: 686850 | F32: 88470 | G32: 31640 | H32: 0 | I32: 57080 | J32: =SUM(E32:I32) -> 864040 | L32: 0 | N32: 530000 | P32: =IF(O32="","",O32+E32-L32-N32) | R32: =IF(OR(Q32="",P32=""),"",Q32-P32) | S32: =IF(R32="","",IF(ABS(R32)<=Léeme!$B$12,"Cuadra",IF(R32<0,"Faltante","Sobrante"))) | T32: No
A33: 45676 | B33: Jardín | D33: Excel | E33: 446590 | F33: 57390 | G33: 24170 | H33: 0 | I33: 40060 | J33: =SUM(E33:I33) -> 568210 | L33: 0 | N33: 0 | P33: =IF(O33="","",O33+E33-L33-N33) | R33: =IF(OR(Q33="",P33=""),"",Q33-P33) | S33: =IF(R33="","",IF(ABS(R33)<=Léeme!$B$12,"Cuadra",IF(R33<0,"Faltante","Sobrante"))) | T33: No
A34: 45678 | B34: Centro | D34: Excel | E34: 255110 | F34: 32000 | G34: 14590 | H34: 0 | I34: 22660 | J34: =SUM(E34:I34) -> 324360 | L34: 23690 | M34: Verdulería | N34: 0 | P34: =IF(O34="","",O34+E34-L34-N34) | R34: =IF(OR(Q34="",P34=""),"",Q34-P34) | S34: =IF(R34="","",IF(ABS(R34)<=Léeme!$B$12,"Cuadra",IF(R34<0,"Faltante","Sobrante"))) | T34: No
A35: 45678 | B35: Jardín | D35: Excel | E35: 219570 | F35: 25710 | G35: 11030 | H35: 0 | I35: 16950 | J35: =SUM(E35:I35) -> 273260 | L35: 5080 | M35: Limpieza | N35: 0 | P35: =IF(O35="","",O35+E35-L35-N35) | R35: =IF(OR(Q35="",P35=""),"",Q35-P35) | S35: =IF(R35="","",IF(ABS(R35)<=Léeme!$B$12,"Cuadra",IF(R35<0,"Faltante","Sobrante"))) | T35: No
A36: 45679 | B36: Centro | D36: Excel | E36: 277260 | F36: 37860 | G36: 14570 | H36: 0 | I36: 23190 | J36: =SUM(E36:I36) -> 352880 | L36: 6660 | M36: Limpieza | N36: 196000 | P36: =IF(O36="","",O36+E36-L36-N36) | R36: =IF(OR(Q36="",P36=""),"",Q36-P36) | S36: =IF(R36="","",IF(ABS(R36)<=Léeme!$B$12,"Cuadra",IF(R36<0,"Faltante","Sobrante"))) | T36: No
A37: 45679 | B37: Jardín | D37: Excel | E37: 195620 | F37: 26130 | G37: 10410 | H37: 0 | I37: 15470 | J37: =SUM(E37:I37) -> 247630 | L37: 0 | N37: 0 | P37: =IF(O37="","",O37+E37-L37-N37) | R37: =IF(OR(Q37="",P37=""),"",Q37-P37) | S37: =IF(R37="","",IF(ABS(R37)<=Léeme!$B$12,"Cuadra",IF(R37<0,"Faltante","Sobrante"))) | T37: No
A38: 45680 | B38: Centro | D38: Excel | E38: 244130 | F38: 30160 | G38: 11160 | H38: 0 | I38: 17210 | J38: =SUM(E38:I38) -> 302660 | L38: 0 | N38: 0 | P38: =IF(O38="","",O38+E38-L38-N38) | R38: =IF(OR(Q38="",P38=""),"",Q38-P38) | S38: =IF(R38="","",IF(ABS(R38)<=Léeme!$B$12,"Cuadra",IF(R38<0,"Faltante","Sobrante"))) | T38: No
A39: 45680 | B39: Jardín | D39: Excel | E39: 207440 | F39: 25910 | G39: 10460 | H39: 0 | I39: 16760 | J39: =SUM(E39:I39) -> 260570 | L39: 0 | N39: 0 | P39: =IF(O39="","",O39+E39-L39-N39) | R39: =IF(OR(Q39="",P39=""),"",Q39-P39) | S39: =IF(R39="","",IF(ABS(R39)<=Léeme!$B$12,"Cuadra",IF(R39<0,"Faltante","Sobrante"))) | T39: No
A40: 45681 | B40: Centro | D40: Excel | E40: 271530 | F40: 39090 | G40: 14750 | H40: 0 | I40: 24830 | J40: =SUM(E40:I40) -> 350200 | L40: 0 | N40: 0 | P40: =IF(O40="","",O40+E40-L40-N40) | R40: =IF(OR(Q40="",P40=""),"",Q40-P40) | S40: =IF(R40="","",IF(ABS(R40)<=Léeme!$B$12,"Cuadra",IF(R40<0,"Faltante","Sobrante"))) | T40: No
A41: 45681 | B41: Jardín | D41: Excel | E41: 185780 | F41: 24010 | G41: 10130 | H41: 0 | I41: 16410 | J41: =SUM(E41:I41) -> 236330 | L41: 21490 | M41: Verdulería | N41: 0 | P41: =IF(O41="","",O41+E41-L41-N41) | R41: =IF(OR(Q41="",P41=""),"",Q41-P41) | S41: =IF(R41="","",IF(ABS(R41)<=Léeme!$B$12,"Cuadra",IF(R41<0,"Faltante","Sobrante"))) | T41: No
A42: 45682 | B42: Centro | D42: Excel | E42: 414940 | F42: 53810 | G42: 19840 | H42: 0 | I42: 33190 | J42: =SUM(E42:I42) -> 521780 | L42: 0 | N42: 329000 | P42: =IF(O42="","",O42+E42-L42-N42) | R42: =IF(OR(Q42="",P42=""),"",Q42-P42) | S42: =IF(R42="","",IF(ABS(R42)<=Léeme!$B$12,"Cuadra",IF(R42<0,"Faltante","Sobrante"))) | T42: No
A43: 45682 | B43: Jardín | D43: Excel | E43: 327180 | F43: 37210 | G43: 15540 | H43: 0 | I43: 24810 | J43: =SUM(E43:I43) -> 404740 | L43: 0 | N43: 0 | P43: =IF(O43="","",O43+E43-L43-N43) | R43: =IF(OR(Q43="",P43=""),"",Q43-P43) | S43: =IF(R43="","",IF(ABS(R43)<=Léeme!$B$12,"Cuadra",IF(R43<0,"Faltante","Sobrante"))) | T43: No
A44: 45683 | B44: Centro | D44: Excel | E44: 722230 | F44: 97210 | G44: 39960 | H44: 0 | I44: 68540 | J44: =SUM(E44:I44) -> 927940 | L44: 17580 | M44: Verdulería | N44: 0 | P44: =IF(O44="","",O44+E44-L44-N44) | R44: =IF(OR(Q44="",P44=""),"",Q44-P44) | S44: =IF(R44="","",IF(ABS(R44)<=Léeme!$B$12,"Cuadra",IF(R44<0,"Faltante","Sobrante"))) | T44: No
A45: 45683 | B45: Jardín | D45: Excel | E45: 510980 | F45: 60420 | G45: 22330 | H45: 0 | I45: 40030 | J45: =SUM(E45:I45) -> 633760 | L45: 3830 | M45: Limpieza | N45: 0 | P45: =IF(O45="","",O45+E45-L45-N45) | R45: =IF(OR(Q45="",P45=""),"",Q45-P45) | S45: =IF(R45="","",IF(ABS(R45)<=Léeme!$B$12,"Cuadra",IF(R45<0,"Faltante","Sobrante"))) | T45: No
A46: 45685 | B46: Centro | D46: Excel | E46: 272570 | F46: 34840 | G46: 15180 | H46: 0 | I46: 22790 | J46: =SUM(E46:I46) -> 345380 | L46: 8420 | M46: Verdulería | N46: 241000 | P46: =IF(O46="","",O46+E46-L46-N46) | R46: =IF(OR(Q46="",P46=""),"",Q46-P46) | S46: =IF(R46="","",IF(ABS(R46)<=Léeme!$B$12,"Cuadra",IF(R46<0,"Faltante","Sobrante"))) | T46: No
A47: 45685 | B47: Jardín | D47: Excel | E47: 209840 | F47: 31070 | G47: 12380 | H47: 0 | I47: 19350 | J47: =SUM(E47:I47) -> 272640 | L47: 18450 | M47: Verdulería | N47: 0 | P47: =IF(O47="","",O47+E47-L47-N47) | R47: =IF(OR(Q47="",P47=""),"",Q47-P47) | S47: =IF(R47="","",IF(ABS(R47)<=Léeme!$B$12,"Cuadra",IF(R47<0,"Faltante","Sobrante"))) | T47: No
A48: 45686 | B48: Centro | D48: Excel | E48: 245500 | F48: 34180 | G48: 13510 | H48: 0 | I48: 18960 | J48: =SUM(E48:I48) -> 312150 | L48: 0 | N48: 0 | P48: =IF(O48="","",O48+E48-L48-N48) | R48: =IF(OR(Q48="",P48=""),"",Q48-P48) | S48: =IF(R48="","",IF(ABS(R48)<=Léeme!$B$12,"Cuadra",IF(R48<0,"Faltante","Sobrante"))) | T48: No
A49: 45686 | B49: Jardín | D49: Excel | E49: 210510 | F49: 26520 | G49: 10700 | H49: 0 | I49: 17440 | J49: =SUM(E49:I49) -> 265170 | L49: 0 | N49: 0 | P49: =IF(O49="","",O49+E49-L49-N49) | R49: =IF(OR(Q49="",P49=""),"",Q49-P49) | S49: =IF(R49="","",IF(ABS(R49)<=Léeme!$B$12,"Cuadra",IF(R49<0,"Faltante","Sobrante"))) | T49: No
A50: 45687 | B50: Centro | D50: Excel | E50: 244070 | F50: 37770 | G50: 13080 | H50: 0 | I50: 22520 | J50: =SUM(E50:I50) -> 317440 | L50: 3460 | M50: Delivery | N50: 133000 | P50: =IF(O50="","",O50+E50-L50-N50) | R50: =IF(OR(Q50="",P50=""),"",Q50-P50) | S50: =IF(R50="","",IF(ABS(R50)<=Léeme!$B$12,"Cuadra",IF(R50<0,"Faltante","Sobrante"))) | T50: No
A51: 45687 | B51: Jardín | D51: Excel | E51: 174460 | F51: 22480 | G51: 10780 | H51: 0 | I51: 16690 | J51: =SUM(E51:I51) -> 224410 | L51: 0 | N51: 124000 | P51: =IF(O51="","",O51+E51-L51-N51) | R51: =IF(OR(Q51="",P51=""),"",Q51-P51) | S51: =IF(R51="","",IF(ABS(R51)<=Léeme!$B$12,"Cuadra",IF(R51<0,"Faltante","Sobrante"))) | T51: No
A52: 45688 | B52: Centro | D52: Excel | E52: 255820 | F52: 34620 | G52: 12830 | H52: 0 | I52: 20480 | J52: =SUM(E52:I52) -> 323750 | L52: 8980 | M52: Verdulería | N52: 0 | P52: =IF(O52="","",O52+E52-L52-N52) | R52: =IF(OR(Q52="",P52=""),"",Q52-P52) | S52: =IF(R52="","",IF(ABS(R52)<=Léeme!$B$12,"Cuadra",IF(R52<0,"Faltante","Sobrante"))) | T52: No
A53: 45688 | B53: Jardín | D53: Excel | E53: 198160 | F53: 25640 | G53: 10300 | H53: 0 | I53: 16860 | J53: =SUM(E53:I53) -> 250960 | L53: 0 | N53: 0 | P53: =IF(O53="","",O53+E53-L53-N53) | R53: =IF(OR(Q53="",P53=""),"",Q53-P53) | S53: =IF(R53="","",IF(ABS(R53)<=Léeme!$B$12,"Cuadra",IF(R53<0,"Faltante","Sobrante"))) | T53: No
A54: 45689 | B54: Centro | D54: Excel | E54: 422290 | F54: 58300 | G54: 22340 | H54: 0 | I54: 38870 | J54: =SUM(E54:I54) -> 541800 | L54: 15520 | M54: Verdulería | N54: 250000 | P54: =IF(O54="","",O54+E54-L54-N54) | R54: =IF(OR(Q54="",P54=""),"",Q54-P54) | S54: =IF(R54="","",IF(ABS(R54)<=Léeme!$B$12,"Cuadra",IF(R54<0,"Faltante","Sobrante"))) | T54: No
A55: 45689 | B55: Jardín | D55: Excel | E55: 348230 | F55: 47860 | G55: 17540 | H55: 0 | I55: 28220 | J55: =SUM(E55:I55) -> 441850 | L55: 0 | N55: 0 | P55: =IF(O55="","",O55+E55-L55-N55) | R55: =IF(OR(Q55="",P55=""),"",Q55-P55) | S55: =IF(R55="","",IF(ABS(R55)<=Léeme!$B$12,"Cuadra",IF(R55<0,"Faltante","Sobrante"))) | T55: No
A56: 45690 | B56: Centro | D56: Excel | E56: 700750 | F56: 82570 | G56: 38940 | H56: 0 | I56: 63290 | J56: =SUM(E56:I56) -> 885550 | L56: 4300 | M56: Delivery | N56: 420000 | P56: =IF(O56="","",O56+E56-L56-N56) | R56: =IF(OR(Q56="",P56=""),"",Q56-P56) | S56: =IF(R56="","",IF(ABS(R56)<=Léeme!$B$12,"Cuadra",IF(R56<0,"Faltante","Sobrante"))) | T56: No
A57: 45690 | B57: Jardín | D57: Excel | E57: 492960 | F57: 63920 | G57: 29320 | H57: 0 | I57: 41300 | J57: =SUM(E57:I57) -> 627500 | L57: 0 | N57: 374000 | P57: =IF(O57="","",O57+E57-L57-N57) | R57: =IF(OR(Q57="",P57=""),"",Q57-P57) | S57: =IF(R57="","",IF(ABS(R57)<=Léeme!$B$12,"Cuadra",IF(R57<0,"Faltante","Sobrante"))) | T57: No
A58: 45692 | B58: Centro | D58: Excel | E58: 285320 | F58: 42560 | G58: 17630 | H58: 0 | I58: 29210 | J58: =SUM(E58:I58) -> 374720 | L58: 0 | N58: 0 | P58: =IF(O58="","",O58+E58-L58-N58) | R58: =IF(OR(Q58="",P58=""),"",Q58-P58) | S58: =IF(R58="","",IF(ABS(R58)<=Léeme!$B$12,"Cuadra",IF(R58<0,"Faltante","Sobrante"))) | T58: No
A59: 45692 | B59: Jardín | D59: Excel | E59: 188950 | F59: 26120 | G59: 10900 | H59: 0 | I59: 16230 | J59: =SUM(E59:I59) -> 242200 | L59: 8270 | M59: Verdulería | N59: 0 | P59: =IF(O59="","",O59+E59-L59-N59) | R59: =IF(OR(Q59="",P59=""),"",Q59-P59) | S59: =IF(R59="","",IF(ABS(R59)<=Léeme!$B$12,"Cuadra",IF(R59<0,"Faltante","Sobrante"))) | T59: No
A60: 45693 | B60: Centro | D60: Excel | E60: 275270 | F60: 32810 | G60: 12730 | H60: 0 | I60: 24310 | J60: =SUM(E60:I60) -> 345120 | L60: 0 | N60: 0 | P60: =IF(O60="","",O60+E60-L60-N60) | R60: =IF(OR(Q60="",P60=""),"",Q60-P60) | S60: =IF(R60="","",IF(ABS(R60)<=Léeme!$B$12,"Cuadra",IF(R60<0,"Faltante","Sobrante"))) | T60: No
A61: 45693 | B61: Jardín | D61: Excel | E61: 207570 | F61: 28800 | G61: 12300 | H61: 0 | I61: 19150 | J61: =SUM(E61:I61) -> 267820 | L61: 0 | N61: 0 | P61: =IF(O61="","",O61+E61-L61-N61) | R61: =IF(OR(Q61="",P61=""),"",Q61-P61) | S61: =IF(R61="","",IF(ABS(R61)<=Léeme!$B$12,"Cuadra",IF(R61<0,"Faltante","Sobrante"))) | T61: No
A62: 45694 | B62: Centro | D62: Excel | E62: 252140 | F62: 32930 | G62: 12210 | H62: 0 | I62: 21240 | J62: =SUM(E62:I62) -> 318520 | L62: 23930 | M62: Verdulería | N62: 184000 | P62: =IF(O62="","",O62+E62-L62-N62) | R62: =IF(OR(Q62="",P62=""),"",Q62-P62) | S62: =IF(R62="","",IF(ABS(R62)<=Léeme!$B$12,"Cuadra",IF(R62<0,"Faltante","Sobrante"))) | T62: No
A63: 45694 | B63: Jardín | D63: Excel | E63: 208120 | F63: 27810 | G63: 12460 | H63: 0 | I63: 17290 | J63: =SUM(E63:I63) -> 265680 | L63: 0 | N63: 0 | P63: =IF(O63="","",O63+E63-L63-N63) | R63: =IF(OR(Q63="",P63=""),"",Q63-P63) | S63: =IF(R63="","",IF(ABS(R63)<=Léeme!$B$12,"Cuadra",IF(R63<0,"Faltante","Sobrante"))) | T63: No
A64: 45695 | B64: Centro | D64: Excel | E64: 279930 | F64: 33630 | G64: 13740 | H64: 0 | I64: 23730 | J64: =SUM(E64:I64) -> 351030 | L64: 21460 | M64: Verdulería | N64: 215000 | P64: =IF(O64="","",O64+E64-L64-N64) | R64: =IF(OR(Q64="",P64=""),"",Q64-P64) | S64: =IF(R64="","",IF(ABS(R64)<=Léeme!$B$12,"Cuadra",IF(R64<0,"Faltante","Sobrante"))) | T64: No
A65: 45695 | B65: Jardín | D65: Excel | E65: 220580 | F65: 28130 | G65: 11980 | H65: 0 | I65: 20400 | J65: =SUM(E65:I65) -> 281090 | L65: 22540 | M65: Verdulería | N65: 0 | P65: =IF(O65="","",O65+E65-L65-N65) | R65: =IF(OR(Q65="",P65=""),"",Q65-P65) | S65: =IF(R65="","",IF(ABS(R65)<=Léeme!$B$12,"Cuadra",IF(R65<0,"Faltante","Sobrante"))) | T65: No
A66: 45696 | B66: Centro | D66: Excel | E66: 406770 | F66: 54410 | G66: 20190 | H66: 0 | I66: 38160 | J66: =SUM(E66:I66) -> 519530 | L66: 8690 | M66: Limpieza | N66: 261000 | P66: =IF(O66="","",O66+E66-L66-N66) | R66: =IF(OR(Q66="",P66=""),"",Q66-P66) | S66: =IF(R66="","",IF(ABS(R66)<=Léeme!$B$12,"Cuadra",IF(R66<0,"Faltante","Sobrante"))) | T66: No
A67: 45696 | B67: Jardín | D67: Excel | E67: 310900 | F67: 40560 | G67: 15860 | H67: 0 | I67: 24840 | J67: =SUM(E67:I67) -> 392160 | L67: 0 | N67: 0 | P67: =IF(O67="","",O67+E67-L67-N67) | R67: =IF(OR(Q67="",P67=""),"",Q67-P67) | S67: =IF(R67="","",IF(ABS(R67)<=Léeme!$B$12,"Cuadra",IF(R67<0,"Faltante","Sobrante"))) | T67: No
A68: 45697 | B68: Centro | D68: Excel | E68: 698650 | F68: 105960 | G68: 43180 | H68: 0 | I68: 69860 | J68: =SUM(E68:I68) -> 917650 | L68: 0 | N68: 365000 | P68: =IF(O68="","",O68+E68-L68-N68) | R68: =IF(OR(Q68="",P68=""),"",Q68-P68) | S68: =IF(R68="","",IF(ABS(R68)<=Léeme!$B$12,"Cuadra",IF(R68<0,"Faltante","Sobrante"))) | T68: No
A69: 45697 | B69: Jardín | D69: Excel | E69: 544280 | F69: 68000 | G69: 30580 | H69: 0 | I69: 50070 | J69: =SUM(E69:I69) -> 692930 | L69: 0 | N69: 313000 | P69: =IF(O69="","",O69+E69-L69-N69) | R69: =IF(OR(Q69="",P69=""),"",Q69-P69) | S69: =IF(R69="","",IF(ABS(R69)<=Léeme!$B$12,"Cuadra",IF(R69<0,"Faltante","Sobrante"))) | T69: No
A70: 45699 | B70: Centro | D70: Excel | E70: 274210 | F70: 32470 | G70: 13610 | H70: 0 | I70: 23420 | J70: =SUM(E70:I70) -> 343710 | L70: 0 | N70: 0 | P70: =IF(O70="","",O70+E70-L70-N70) | R70: =IF(OR(Q70="",P70=""),"",Q70-P70) | S70: =IF(R70="","",IF(ABS(R70)<=Léeme!$B$12,"Cuadra",IF(R70<0,"Faltante","Sobrante"))) | T70: No
A71: 45699 | B71: Jardín | D71: Excel | E71: 210730 | F71: 25700 | G71: 10400 | H71: 0 | I71: 18030 | J71: =SUM(E71:I71) -> 264860 | L71: 15620 | M71: Verdulería | N71: 0 | P71: =IF(O71="","",O71+E71-L71-N71) | R71: =IF(OR(Q71="",P71=""),"",Q71-P71) | S71: =IF(R71="","",IF(ABS(R71)<=Léeme!$B$12,"Cuadra",IF(R71<0,"Faltante","Sobrante"))) | T71: No
A72: 45700 | B72: Centro | D72: Excel | E72: 250340 | F72: 33980 | G72: 13670 | H72: 0 | I72: 22160 | J72: =SUM(E72:I72) -> 320150 | L72: 0 | N72: 0 | P72: =IF(O72="","",O72+E72-L72-N72) | R72: =IF(OR(Q72="",P72=""),"",Q72-P72) | S72: =IF(R72="","",IF(ABS(R72)<=Léeme!$B$12,"Cuadra",IF(R72<0,"Faltante","Sobrante"))) | T72: No
A73: 45700 | B73: Jardín | D73: Excel | E73: 188540 | F73: 24480 | G73: 9520 | H73: 0 | I73: 16100 | J73: =SUM(E73:I73) -> 238640 | L73: 0 | N73: 0 | P73: =IF(O73="","",O73+E73-L73-N73) | R73: =IF(OR(Q73="",P73=""),"",Q73-P73) | S73: =IF(R73="","",IF(ABS(R73)<=Léeme!$B$12,"Cuadra",IF(R73<0,"Faltante","Sobrante"))) | T73: No
A74: 45701 | B74: Centro | D74: Excel | E74: 284300 | F74: 34100 | G74: 15940 | H74: 0 | I74: 25300 | J74: =SUM(E74:I74) -> 359640 | L74: 0 | N74: 209000 | P74: =IF(O74="","",O74+E74-L74-N74) | R74: =IF(OR(Q74="",P74=""),"",Q74-P74) | S74: =IF(R74="","",IF(ABS(R74)<=Léeme!$B$12,"Cuadra",IF(R74<0,"Faltante","Sobrante"))) | T74: No
A75: 45701 | B75: Jardín | D75: Excel | E75: 204640 | F75: 27610 | G75: 12200 | H75: 0 | I75: 18630 | J75: =SUM(E75:I75) -> 263080 | L75: 0 | N75: 0 | P75: =IF(O75="","",O75+E75-L75-N75) | R75: =IF(OR(Q75="",P75=""),"",Q75-P75) | S75: =IF(R75="","",IF(ABS(R75)<=Léeme!$B$12,"Cuadra",IF(R75<0,"Faltante","Sobrante"))) | T75: No
A76: 45702 | B76: Centro | D76: Excel | E76: 289250 | F76: 43930 | G76: 17850 | H76: 0 | I76: 26100 | J76: =SUM(E76:I76) -> 377130 | L76: 0 | N76: 200000 | P76: =IF(O76="","",O76+E76-L76-N76) | R76: =IF(OR(Q76="",P76=""),"",Q76-P76) | S76: =IF(R76="","",IF(ABS(R76)<=Léeme!$B$12,"Cuadra",IF(R76<0,"Faltante","Sobrante"))) | T76: No
A77: 45702 | B77: Jardín | D77: Excel | E77: 209960 | F77: 30550 | G77: 12160 | H77: 0 | I77: 21050 | J77: =SUM(E77:I77) -> 273720 | L77: 8150 | M77: Limpieza | N77: 0 | P77: =IF(O77="","",O77+E77-L77-N77) | R77: =IF(OR(Q77="",P77=""),"",Q77-P77) | S77: =IF(R77="","",IF(ABS(R77)<=Léeme!$B$12,"Cuadra",IF(R77<0,"Faltante","Sobrante"))) | T77: No
A78: 45703 | B78: Centro | D78: Excel | E78: 423320 | F78: 52710 | G78: 21560 | H78: 0 | I78: 37840 | J78: =SUM(E78:I78) -> 535430 | L78: 0 | N78: 229000 | P78: =IF(O78="","",O78+E78-L78-N78) | R78: =IF(OR(Q78="",P78=""),"",Q78-P78) | S78: =IF(R78="","",IF(ABS(R78)<=Léeme!$B$12,"Cuadra",IF(R78<0,"Faltante","Sobrante"))) | T78: No
A79: 45703 | B79: Jardín | D79: Excel | E79: 302560 | F79: 36020 | G79: 14490 | H79: 0 | I79: 25140 | J79: =SUM(E79:I79) -> 378210 | L79: 4890 | M79: Limpieza | N79: 0 | P79: =IF(O79="","",O79+E79-L79-N79) | R79: =IF(OR(Q79="",P79=""),"",Q79-P79) | S79: =IF(R79="","",IF(ABS(R79)<=Léeme!$B$12,"Cuadra",IF(R79<0,"Faltante","Sobrante"))) | T79: No
A80: 45704 | B80: Centro | D80: Excel | E80: 631920 | F80: 91530 | G80: 36730 | H80: 0 | I80: 59830 | J80: =SUM(E80:I80) -> 820010 | L80: 7580 | M80: Envases | N80: 0 | P80: =IF(O80="","",O80+E80-L80-N80) | R80: =IF(OR(Q80="",P80=""),"",Q80-P80) | S80: =IF(R80="","",IF(ABS(R80)<=Léeme!$B$12,"Cuadra",IF(R80<0,"Faltante","Sobrante"))) | T80: No
A81: 45704 | B81: Jardín | D81: Excel | E81: 509680 | F81: 77950 | G81: 33780 | H81: 0 | I81: 52210 | J81: =SUM(E81:I81) -> 673620 | L81: 6780 | M81: Envases | N81: 321000 | P81: =IF(O81="","",O81+E81-L81-N81) | R81: =IF(OR(Q81="",P81=""),"",Q81-P81) | S81: =IF(R81="","",IF(ABS(R81)<=Léeme!$B$12,"Cuadra",IF(R81<0,"Faltante","Sobrante"))) | T81: No
A82: 45706 | B82: Centro | D82: Excel | E82: 259270 | F82: 32870 | G82: 14430 | H82: 0 | I82: 22060 | J82: =SUM(E82:I82) -> 328630 | L82: 16880 | M82: Verdulería | N82: 0 | P82: =IF(O82="","",O82+E82-L82-N82) | R82: =IF(OR(Q82="",P82=""),"",Q82-P82) | S82: =IF(R82="","",IF(ABS(R82)<=Léeme!$B$12,"Cuadra",IF(R82<0,"Faltante","Sobrante"))) | T82: No
A83: 45706 | B83: Jardín | D83: Excel | E83: 220540 | F83: 25770 | G83: 12090 | H83: 0 | I83: 18860 | J83: =SUM(E83:I83) -> 277260 | L83: 0 | N83: 0 | P83: =IF(O83="","",O83+E83-L83-N83) | R83: =IF(OR(Q83="",P83=""),"",Q83-P83) | S83: =IF(R83="","",IF(ABS(R83)<=Léeme!$B$12,"Cuadra",IF(R83<0,"Faltante","Sobrante"))) | T83: No
A84: 45707 | B84: Centro | D84: Excel | E84: 285050 | F84: 38320 | G84: 15240 | H84: 0 | I84: 30620 | J84: =SUM(E84:I84) -> 369230 | L84: 0 | N84: 0 | P84: =IF(O84="","",O84+E84-L84-N84) | R84: =IF(OR(Q84="",P84=""),"",Q84-P84) | S84: =IF(R84="","",IF(ABS(R84)<=Léeme!$B$12,"Cuadra",IF(R84<0,"Faltante","Sobrante"))) | T84: No
A85: 45707 | B85: Jardín | D85: Excel | E85: 185560 | F85: 28360 | G85: 11690 | H85: 0 | I85: 17490 | J85: =SUM(E85:I85) -> 243100 | L85: 16430 | M85: Verdulería | N85: 0 | P85: =IF(O85="","",O85+E85-L85-N85) | R85: =IF(OR(Q85="",P85=""),"",Q85-P85) | S85: =IF(R85="","",IF(ABS(R85)<=Léeme!$B$12,"Cuadra",IF(R85<0,"Faltante","Sobrante"))) | T85: No
A86: 45708 | B86: Centro | D86: Excel | E86: 261710 | F86: 41150 | G86: 17200 | H86: 0 | I86: 27170 | J86: =SUM(E86:I86) -> 347230 | L86: 0 | N86: 0 | P86: =IF(O86="","",O86+E86-L86-N86) | R86: =IF(OR(Q86="",P86=""),"",Q86-P86) | S86: =IF(R86="","",IF(ABS(R86)<=Léeme!$B$12,"Cuadra",IF(R86<0,"Faltante","Sobrante"))) | T86: No
A87: 45708 | B87: Jardín | D87: Excel | E87: 192450 | F87: 25290 | G87: 10940 | H87: 0 | I87: 18100 | J87: =SUM(E87:I87) -> 246780 | L87: 0 | N87: 0 | P87: =IF(O87="","",O87+E87-L87-N87) | R87: =IF(OR(Q87="",P87=""),"",Q87-P87) | S87: =IF(R87="","",IF(ABS(R87)<=Léeme!$B$12,"Cuadra",IF(R87<0,"Faltante","Sobrante"))) | T87: No
A88: 45709 | B88: Centro | D88: Excel | E88: 233050 | F88: 32250 | G88: 13700 | H88: 0 | I88: 24490 | J88: =SUM(E88:I88) -> 303490 | L88: 19830 | M88: Verdulería | N88: 141000 | P88: =IF(O88="","",O88+E88-L88-N88) | R88: =IF(OR(Q88="",P88=""),"",Q88-P88) | S88: =IF(R88="","",IF(ABS(R88)<=Léeme!$B$12,"Cuadra",IF(R88<0,"Faltante","Sobrante"))) | T88: No
A89: 45709 | B89: Jardín | D89: Excel | E89: 223700 | F89: 31130 | G89: 12860 | H89: 0 | I89: 24170 | J89: =SUM(E89:I89) -> 291860 | L89: 10120 | M89: Verdulería | N89: 169000 | P89: =IF(O89="","",O89+E89-L89-N89) | R89: =IF(OR(Q89="",P89=""),"",Q89-P89) | S89: =IF(R89="","",IF(ABS(R89)<=Léeme!$B$12,"Cuadra",IF(R89<0,"Faltante","Sobrante"))) | T89: No
A90: 45710 | B90: Centro | D90: Excel | E90: 448380 | F90: 67450 | G90: 23340 | H90: 0 | I90: 46980 | J90: =SUM(E90:I90) -> 586150 | L90: 0 | N90: 343000 | P90: =IF(O90="","",O90+E90-L90-N90) | R90: =IF(OR(Q90="",P90=""),"",Q90-P90) | S90: =IF(R90="","",IF(ABS(R90)<=Léeme!$B$12,"Cuadra",IF(R90<0,"Faltante","Sobrante"))) | T90: No
A91: 45710 | B91: Jardín | D91: Excel | E91: 355690 | F91: 51170 | G91: 19150 | H91: 0 | I91: 33530 | J91: =SUM(E91:I91) -> 459540 | L91: 0 | N91: 0 | P91: =IF(O91="","",O91+E91-L91-N91) | R91: =IF(OR(Q91="",P91=""),"",Q91-P91) | S91: =IF(R91="","",IF(ABS(R91)<=Léeme!$B$12,"Cuadra",IF(R91<0,"Faltante","Sobrante"))) | T91: No
A92: 45711 | B92: Centro | D92: Excel | E92: 678190 | F92: 99700 | G92: 45290 | H92: 0 | I92: 73550 | J92: =SUM(E92:I92) -> 896730 | L92: 4850 | M92: Delivery | N92: 573000 | P92: =IF(O92="","",O92+E92-L92-N92) | R92: =IF(OR(Q92="",P92=""),"",Q92-P92) | S92: =IF(R92="","",IF(ABS(R92)<=Léeme!$B$12,"Cuadra",IF(R92<0,"Faltante","Sobrante"))) | T92: No
A93: 45711 | B93: Jardín | D93: Excel | E93: 520190 | F93: 73780 | G93: 29080 | H93: 0 | I93: 53080 | J93: =SUM(E93:I93) -> 676130 | L93: 0 | N93: 0 | P93: =IF(O93="","",O93+E93-L93-N93) | R93: =IF(OR(Q93="",P93=""),"",Q93-P93) | S93: =IF(R93="","",IF(ABS(R93)<=Léeme!$B$12,"Cuadra",IF(R93<0,"Faltante","Sobrante"))) | T93: No
A94: 45713 | B94: Centro | D94: Excel | E94: 257450 | F94: 35530 | G94: 14670 | H94: 0 | I94: 27380 | J94: =SUM(E94:I94) -> 335030 | L94: 0 | N94: 157000 | P94: =IF(O94="","",O94+E94-L94-N94) | R94: =IF(OR(Q94="",P94=""),"",Q94-P94) | S94: =IF(R94="","",IF(ABS(R94)<=Léeme!$B$12,"Cuadra",IF(R94<0,"Faltante","Sobrante"))) | T94: No
A95: 45713 | B95: Jardín | D95: Excel | E95: 209190 | F95: 30280 | G95: 11810 | H95: 0 | I95: 20560 | J95: =SUM(E95:I95) -> 271840 | L95: 18200 | M95: Verdulería | N95: 0 | P95: =IF(O95="","",O95+E95-L95-N95) | R95: =IF(OR(Q95="",P95=""),"",Q95-P95) | S95: =IF(R95="","",IF(ABS(R95)<=Léeme!$B$12,"Cuadra",IF(R95<0,"Faltante","Sobrante"))) | T95: No
A96: 45714 | B96: Centro | D96: Excel | E96: 285740 | F96: 42570 | G96: 17980 | H96: 0 | I96: 29450 | J96: =SUM(E96:I96) -> 375740 | L96: 12540 | M96: Envases | N96: 0 | P96: =IF(O96="","",O96+E96-L96-N96) | R96: =IF(OR(Q96="",P96=""),"",Q96-P96) | S96: =IF(R96="","",IF(ABS(R96)<=Léeme!$B$12,"Cuadra",IF(R96<0,"Faltante","Sobrante"))) | T96: No
A97: 45714 | B97: Jardín | D97: Excel | E97: 183430 | F97: 25710 | G97: 9760 | H97: 0 | I97: 16880 | J97: =SUM(E97:I97) -> 235780 | L97: 0 | N97: 0 | P97: =IF(O97="","",O97+E97-L97-N97) | R97: =IF(OR(Q97="",P97=""),"",Q97-P97) | S97: =IF(R97="","",IF(ABS(R97)<=Léeme!$B$12,"Cuadra",IF(R97<0,"Faltante","Sobrante"))) | T97: No
A98: 45715 | B98: Centro | D98: Excel | E98: 242150 | F98: 28650 | G98: 13180 | H98: 0 | I98: 21460 | J98: =SUM(E98:I98) -> 305440 | L98: 19260 | M98: Verdulería | N98: 0 | P98: =IF(O98="","",O98+E98-L98-N98) | R98: =IF(OR(Q98="",P98=""),"",Q98-P98) | S98: =IF(R98="","",IF(ABS(R98)<=Léeme!$B$12,"Cuadra",IF(R98<0,"Faltante","Sobrante"))) | T98: No
A99: 45715 | B99: Jardín | D99: Excel | E99: 206410 | F99: 30560 | G99: 11990 | H99: 0 | I99: 22840 | J99: =SUM(E99:I99) -> 271800 | L99: 0 | N99: 0 | P99: =IF(O99="","",O99+E99-L99-N99) | R99: =IF(OR(Q99="",P99=""),"",Q99-P99) | S99: =IF(R99="","",IF(ABS(R99)<=Léeme!$B$12,"Cuadra",IF(R99<0,"Faltante","Sobrante"))) | T99: No
A100: 45716 | B100: Centro | D100: Excel | E100: 271460 | F100: 45540 | G100: 16920 | H100: 0 | I100: 30200 | J100: =SUM(E100:I100) -> 364120 | L100: 0 | N100: 203000 | P100: =IF(O100="","",O100+E100-L100-N100) | R100: =IF(OR(Q100="",P100=""),"",Q100-P100) | S100: =IF(R100="","",IF(ABS(R100)<=Léeme!$B$12,"Cuadra",IF(R100<0,"Faltante","Sobrante"))) | T100: No
...

Sheet Pedidos
A1: Fecha | B1: Cliente | C1: Nombre | D1: Importe | E1: Condición | F1: Fuente
A2: 45659 | B2: 3 | C2: Almacén Doña Rosa | D2: 115100 | E2: Cuenta corriente | F2: Excel
A3: 45659 | B3: 14 | C3: Almacén El Trébol | D3: 71800 | E3: Cuenta corriente | F3: Excel
A4: 45660 | B4: 1 | C4: Restaurante La Esquina | D4: 97700 | E4: Cuenta corriente | F4: Excel
A5: 45660 | B5: 6 | C5: Rotisería Sabores | D5: 48600 | E5: Cuenta corriente | F5: Excel
A6: 45660 | B6: 7 | C6: Restaurante Il Forno | D6: 40600 | E6: Cuenta corriente | F6: Excel
A7: 45660 | B7: 10 | C7: Parrilla El Fogón | D7: 53900 | E7: Cuenta corriente | F7: Excel
A8: 45660 | B8: 17 | C8: Rotisería Don Pepe | D8: 40900 | E8: Cuenta corriente | F8: Excel
A9: 45661 | B9: 4 | C9: Bodegón Los Abuelos | D9: 120400 | E9: Cuenta corriente | F9: Excel
A10: 45661 | B10: 5 | C10: Cantina del Puerto | D10: 147600 | E10: Cuenta corriente | F10: Excel
A11: 45661 | B11: 13 | C11: Restaurante Mediterráneo | D11: 40700 | E11: Cuenta corriente | F11: Excel
A12: 45661 | B12: 15 | C12: Comedor Escolar Norte | D12: 126300 | E12: Cuenta corriente | F12: Excel
A13: 45661 | B13: 21 | C13: Restaurante Tierra Nuestra | D13: 87800 | E13: Cuenta corriente | F13: Excel
... A732: 45939 | B732: 18 | C732: Restaurante Las Tinajas | D732: 54700 | E732: Contado | F732: Formulario

Sheet Cobros
A1: Fecha | B1: Cliente | C1: Nombre | D1: Importe | E1: Medio | F1: Fuente
A2: 45676 | B2: 19 | C2: Bar del Centro | D2: 384300 | E2: Sin dato | F2: Excel
A3: 45679 | B3: 3 | C3: Almacén Doña Rosa | D3: 448600 | E3: Sin dato | F3: Excel
A4: 45681 | B4: 7 | C4: Restaurante Il Forno | D4: 171900 | E4: Sin dato | F4: Excel
A5: 45681 | B5: 10 | C5: Parrilla El Fogón | D5: 213500 | E5: Sin dato | F5: Excel
A6: 45681 | B6: 21 | C6: Restaurante Tierra Nuestra | D6: 260100 | E6: Sin dato | F6: Excel
A7: 45682 | B7: 14 | C7: Almacén El Trébol | D7: 307600 | E7: Sin dato | F7: Excel
A8: 45684 | B8: 6 | C8: Rotisería Sabores | D8: 131600 | E8: Sin dato | F8: Excel
A9: 45684 | B9: 13 | C9: Restaurante Mediterráneo | D9: 94800 | E9: Sin dato | F9: Excel
A10: 45685 | B10: 4 | C10: Bodegón Los Abuelos | D10: 457200 | E10: Sin dato | F10: Excel
A11: 45685 | B11: 5 | C11: Cantina del Puerto | D11: 372000 | E11: Sin dato | F11: Excel
A12: 45686 | B12: 15 | C12: Comedor Escolar Norte | D12: 549500 | E12: Sin dato | F12: Excel
A13: 45686 | B13: 17 | C13: Rotisería Don Pepe | D13: 217100 | E13: Sin dato | F13: Excel
... A353: 45939 | B353: 18 | C353: Restaurante Las Tinajas | D353: 54700 | E353: Transferencia | F353: Formulario

Sheet Problemas del Excel
A1: Hoja | B1: Fila | C1: Problema | D1: Lo que decía | E1: Qué se hizo
A2: Enero | B2: 1 | C2: Billetera y transferencia juntas | D2: La columna de billetera virtual recién aparece en abril | E2: Todo queda como transferencia
A3: Enero | B3: 2 | C3: Fecha como texto | D3: Jue 2/1 | E3: Convertida a fecha (año 2025)
A4: Enero | B4: 2 | C4: Monto como texto | D4: Débito: $ 35.160 | E4: Convertido a número
A5: Enero | B5: 2 | C5: Monto como texto | D5: Transferencia: $ 19.770 | E5: Convertido a número
A6: Enero | B6: 3 | C6: Local escrito distinto | D6: 'Jardin' | E6: Unificado como Jardín
A7: Enero | B7: 4 | C7: Monto como texto | D7: Transferencia: $ 21.370 | E7: Convertido a número
A8: Enero | B8: 4 | C8: Monto como texto | D8: Gastos: 12950.- | E8: Convertido a número
A9: Enero | B9: 5 | C9: Monto como texto | D9: Crédito: 10270.- | E9: Convertido a número
A10: Enero | B10: 6 | C10: Monto como texto | D10: Efectivo: 368.810,00 | E10: Convertido a número
A11: Enero | B11: 6 | C11: Monto como texto | D11: Débito: $ 47.260 | E11: Convertido a número
A12: Enero | B12: 7 | C12: Monto como texto | D12: Gastos: 3280.- | E12: Convertido a número
A13: Enero | B13: 8 | C13: Fecha como texto | D13: 05-01-25 | E13: Convertida a fecha (año 2025)
... A1202: Fiado | B1202: 389 | C1202: Monto como texto | D1202: Pedido: 76900.- | E1202: Convertido a número
A1203: Fiado | C1203: Saldo mal arrastrado | D1203: Rotisería Don Pepe 09/01: diferencia de −$ 29.000 | E1203: Se recalcula el saldo desde los movimientos
A1204: Fiado | C1204: Saldo mal arrastrado | D1204: Restaurante Il Forno 10/01: diferencia de +$ 40.000 | E1204: Se recalcula el saldo desde los movimientos
A1205: Fiado | C1205: Saldo mal arrastrado | D1205: Restaurante Tierra Nuestra 10/01: diferencia de −$ 37.000 | E1205: Se recalcula el saldo desde los movimientos
A1206: Fiado | C1206: Saldo mal arrastrado | D1206: Restaurante La Esquina 11/01: diferencia de −$ 21.000 | E1206: Se recalcula el saldo desde los movimientos
A1207: Fiado | C1207: Saldo mal arrastrado | D1207: Comedor Escolar Norte 27/02: diferencia de +$ 25.000 | E1207: Se recalcula el saldo desde los movimientos
A1208: Fiado | C1208: Saldo mal arrastrado | D1208: Rotisería Don Pepe 06/03: diferencia de −$ 54.000 | E1208: Se recalcula el saldo desde los movimientos
A1209: Fiado | C1209: Saldo mal arrastrado | D1209: Parrilla El Fogón 07/03: diferencia de −$ 37.000 | E1209: Se recalcula el saldo desde los movimientos
A1210: Fiado | C1210: Saldo mal arrastrado | D1210: Restaurante Tierra Nuestra 19/03: diferencia de −$ 63.000 | E1210: Se recalcula el saldo desde los movimientos
A1211: Fiado | C1211: Saldo mal arrastrado | D1211: Parrilla El Fogón 29/03: diferencia de −$ 26.000 | E1211: Se recalcula el saldo desde los movimientos
A1212: Fiado | C1212: Saldo mal arrastrado | D1212: Bodegón Los Abuelos 12/04: diferencia de −$ 6.000 | E1212: Se recalcula el saldo desde los movimientos
A1213: Fiado | C1213: Saldo mal arrastrado | D1213: Almacén Los Pinos 22/05: diferencia de −$ 27.000 | E1213: Se recalcula el saldo desde los movimientos
